Workbook

Sheet Cover
A2: GREEN FACTORY 360
A3: Return on Investment (ROI) Model
A5: ="Prepared for: " & 'Client Inputs'!$B$4 -> Prepared for: [Enter Client Company Name]
A6: Prepared by: Sustainability & Decarbonisation Advisory, Geovitas Environmental Services Pvt. Ltd.
A7: Date: July 2026 | Classification: Client Pitch / Pre-Sales Working Model
A10: HOW TO USE THIS MODEL
B12: 1. Go to the 'Client Inputs' tab and enter the client's profile (turnover, energy spend, export exposure, etc.) and choose a GF360 tier — all BLUE cells are editable.
B13: 2. Review 'Pricing Tiers' to confirm the subscription/implementation/advisory fees pulled in for the selected tier.
B14: 3. 'Cost of Inaction' models what the client is exposed to WITHOUT GF360 (CBAM default-value penalties, manual assessment costs, compliance risk).
B15: 4. 'GF360 Investment' and 'GF360 Benefits' build the 5-year cost and savings case; 'ROI Summary' rolls these into Net Benefit, ROI%, Payback, NPV and IRR, with charts.
B16: 5. 'Sensitivity' stress-tests the result under Conservative / Base / Aggressive assumptions and a 2-variable ROI grid.
B17: 6. 'Assumptions & Sources' documents every hardcoded assumption — replace placeholders with client-specific data collected during discovery before using this in a binding proposal.
B18: 7. Four sector reference tabs support auto-ancillary engagements: 'Auto Ancillary Activities' catalogues every major process in the sector with emission scopes; 'Emission Factors (India)' holds Indian default emission factors (CEA grid EF, fuels, materials, transport) plus a quick Scope 1+2 estimator; 'Process Flow Diagrams' maps typical process routes with emission hotspots; 'Custom Process Flow' lets you assemble the client's own route step-by-step from dropdowns, auto-tagging scopes, EF codes and decarbonisation levers.
A20: COLOR LEGEND
B22: ■ | C22: Blue text — hardcoded input. Change these to reflect the client's actual data.
B23: ■ | C23: Black text — formula / calculation. Do not overwrite.
B24: ■ | C24: Green text — link pulling from another worksheet in this workbook.
B26: This is a pitch/pre-sales modelling template. Validate all client-specific figures during discovery before quoting binding numbers.

Sheet Client Inputs
A1: CLIENT INPUTS & ENGAGEMENT PARAMETERS
A3: 1. Company Profile
A4: Client / Company Name | B4: [Enter Client Company Name]
A5: Industry / Sector | B5: General Manufacturing
A6: Annual Turnover (Rs Cr) | B6: 250
A7: Assumed Annual Revenue Growth (%) | B7: 0.08
A8: Number of Manufacturing Facilities | B8: 3
A9: Annual Energy Spend (Rs Lakh) | B9: 450
A10: % Revenue from EU Exports | B10: 0.18
A11: % Revenue from OEM / Tier-1 Customers Requiring ESG Data | B11: 0.4
A12: Current GHG Data Maturity | B12: Manual spreadsheets
A13: Embedded Emissions Intensity (tCO2e per Rs Cr Revenue) | B13: 45
A14: Blended Internal Staff Cost (Rs per person-day) | B14: 4500
A15: Annual Person-Days on Manual Carbon/ESG Data Collection (Without GF360) | B15: 60
A17: 2. GF360 Engagement Parameters
A18: Selected GF360 Tier | B18: Growth
A19: Annual Subscription Fee (Rs Lakh) | B19: =VLOOKUP($B$18,'Pricing Tiers'!$A$4:$E$6,3,FALSE()) -> 8
A20: One-time Implementation / Onboarding Fee (Rs Lakh) | B20: =VLOOKUP($B$18,'Pricing Tiers'!$A$4:$E$6,4,FALSE()) -> 2.5
A21: Advisory / Verification Support Bundle (Rs Lakh per year) | B21: =VLOOKUP($B$18,'Pricing Tiers'!$A$4:$E$6,5,FALSE()) -> 3
A22: Contract Term (Years) | B22: 5
A23: Annual Subscription / Advisory Escalation (%) | B23: 0.05
A24: Automation Efficiency Gain on Manual Reporting Effort (%) | B24: 0.7
A26: 3. Regulatory & Market Assumptions (Editable)
A27: Note: CBAM applies today to steel, aluminium, cement, fertilisers, hydrogen and electricity, with a proposed downstream expansion to further manufactured products (incl. auto components) from 2028. For sectors with no current or anticipated CBAM exposure, set 'CBAM Default-Value Cost Premium' and/or '% Revenue from EU Exports' to 0% to remove this line from the model.
A28: EU CBAM Certificate Price (EUR per tCO2e) | B28: 85
A29: EUR to INR Exchange Rate | B29: 95
A30: CBAM Default-Value Cost Premium (%) | B30: 0.3
A31: Energy Efficiency Savings — Year 1 (%) | B31: 0.03
A32: Energy Efficiency Savings — Year 2 (%) | B32: 0.08
A33: Energy Efficiency Savings — Year 3 Onward (%) | B33: 0.12
A34: Avoided Annual Consultant / Big-4 Assessment Fee (Rs Lakh) | B34: 35
A35: Probability-Weighted Revenue-at-Risk without Compliance (%) | B35: 0.15
A36: GF360 Risk-Mitigation Effectiveness (%) | B36: 0.8
A37: Discount Rate / WACC for NPV (%) | B37: 0.1
A38: Contribution Margin / EBITDA % (Applied to Revenue-at-Risk) | B38: 0.12

Sheet Pricing Tiers
A1: GF360 TIERED PRICING — REFERENCE TABLE
A3: Tier | B3: Target Turnover Band | C3: Annual Subscription (Rs Lakh) | D3: Implementation Fee (Rs Lakh) | E3: Advisory / Verification Bundle (Rs Lakh/yr) | F3: Key Features Included
A4: Starter | B4: < Rs 100 Cr | C4: 3 | D4: 1 | E4: 1.5 | F4: Scope 1 & 2 tracking, basic MRV dashboards, single-facility, self-serve reporting
A5: Growth | B5: Rs 100 – 500 Cr | C5: 8 | D5: 2.5 | E5: 3 | F5: Scope 1/2/3, CBAM/CCTS/BRSR compliance modules, multi-facility, supplier engagement portal, quarterly advisory
A6: Enterprise | B6: > Rs 500 Cr | C6: 18 | D6: 5 | E6: 6 | F6: Full MRV, ERP/API integrations, carbon-credit monetisation support, dedicated Customer Success Manager, verification support
A8: Source: GF360 Value-Based Tiered SaaS pricing strategy, aligned to the Indian/APAC bundled software + advisory market pattern documented in GF360 market research (July 2026, originally scoped for the auto-ancillary sector; applied here as a general cross-industry benchmark). Confirm current published rates before quoting.

Sheet Auto Ancillary Activities
A1: AUTO ANCILLARY SECTOR — ACTIVITY & PROCESS CATALOGUE
A2: All major manufacturing activities available and possible in the Indian auto-component (auto ancillary) sector, with typical energy/material inputs, GHG emission sources, scopes and links to the 'Emission Factors (India)' tab (EF codes). Use this to scope a client's process footprint during discovery and to select the relevant emission factors.
A3: Code | B3: Activity / Process | C3: Description & Typical Components | D3: Key Energy & Material Inputs | E3: Primary GHG Emission Sources | F3: Scope(s) | G3: EF Refs | H3: Decarbonisation / GF360 Levers | J3: SECTOR SEGMENT LIST (feeds the 'Industry / Sector' dropdown on 'Client Inputs')
A4: 1. FOUNDRY & CASTING | J4: General Manufacturing
A5: FC-01 | B5: Induction furnace melting (iron / steel) | C5: Melting of scrap, pig iron and returns for grey/SG iron and steel castings — housings, brackets, brake drums, hubs, crankcases. | D5: Grid electricity (500–800 kWh/t melt); scrap, pig iron, ferroalloys | E5: Purchased electricity for melting and holding | F5: S2 | G5: EF-E1 | H5: Melt scheduling & power factor, lid/insulation upgrades, RE power purchase, yield improvement | J5: Auto Ancillary - Castings & Foundry
A6: FC-02 | B6: Cupola furnace melting | C6: Coke-fired melting for grey iron castings (older foundries). | D6: Foundry coke (~100–140 kg/t melt), limestone | E6: On-site coke combustion | F6: S1 | G6: EF-F7 | H6: Divided-blast cupola, conversion to induction melting, waste-heat recovery | J6: Auto Ancillary - Forgings
A7: FC-03 | B7: Aluminium melting & holding | C7: Tower/crucible/reverberatory furnaces for Al alloy ingot and scrap — alloy wheels, pistons, cylinder heads, EV housings. | D7: FO / NG / LPG or electricity; Al ingot & scrap | E7: Fuel combustion (S1) or electricity (S2); dross losses | F7: S1, S2 | G7: EF-F2, EF-F5, EF-F4, EF-E1 | H7: Efficient tower furnaces, dross reduction, higher scrap (recycled Al) charge, electrification | J7: Auto Ancillary - Machined Components
A8: FC-04 | B8: High-pressure die casting (HPDC) | C8: Molten Al/Zn injected into steel dies — transmission cases, structural castings, EV motor housings. | D8: Electricity (machine, furnace holding); die lube, hydraulic oil | E8: Purchased electricity; holding furnace fuel | F8: S1, S2 | G8: EF-E1, EF-F4 | H8: Servo-hydraulic/toggle upgrades, holding furnace insulation, OEE improvement | J8: Auto Ancillary - Sheet Metal & Stampings
A9: FC-05 | B9: Gravity / low-pressure die casting | C9: Permanent-mould casting of Al — cylinder heads, wheels, brackets. | D9: Electricity; NG/LPG holding; compressed air | E9: Electricity + fuel for holding/ladle preheat | F9: S1, S2 | G9: EF-E1, EF-F5, EF-F4 | H9: Ladle preheat control, insulation, scheduling | J9: Auto Ancillary - Fasteners & Cold Forged
A10: FC-06 | B10: Sand casting (green sand line) | C10: Moulding, pouring and shakeout for iron castings — housings, manifolds, counterweights. | D10: Electricity (sand plant, blowers); bentonite, coal dust, new sand | E10: Electricity; minor process organics (LOI burn-off) | F10: S2 | G10: EF-E1 | H10: Sand-to-metal ratio optimisation, sand reclamation, VFDs on blowers | J10: Auto Ancillary - Heat Treatment (Job Work)
A11: FC-07 | B11: Investment casting (lost wax) | C11: Precision steel/SS castings — turbo parts, rocker arms, small precision components. | D11: Electricity; LPG/NG for dewax & shell firing; wax, zircon/silica slurry | E11: Fuel for burnout & sintering ovens; electricity | F11: S1, S2 | G11: EF-F4, EF-F5, EF-E1 | H11: Oven insulation & scheduling, shell recycling | J11: Auto Ancillary - Surface Treatment & Plating
A12: FC-08 | B12: Core making (cold box / shell) | C12: Resin-bonded sand cores for internal cavities. | D12: Electricity; phenolic/furan resins, amine catalyst; LPG (shell) | E12: Electricity; process VOC/amine emissions (non-GHG); LPG | F12: S1, S2 | G12: EF-E1, EF-F4 | H12: Inorganic binder systems, core package optimisation | J12: Auto Ancillary - Plastic Components
A13: FC-09 | B13: Fettling, grinding & shot blasting | C13: Removal of gates/risers, surface cleaning of castings. | D13: Electricity (grinders, shot blast machines, dust collection) | E13: Purchased electricity | F13: S2 | G13: EF-E1 | H13: High-efficiency motors, blast media management, near-net-shape casting | J13: Auto Ancillary - Rubber & Elastomers
A14: FC-10 | B14: Sand reclamation (thermal / mechanical) | C14: Recovery of used foundry sand for reuse. | D14: Electricity; NG/LPG (thermal reclaim) | E14: Fuel combustion; electricity | F14: S1, S2 | G14: EF-F5, EF-F4, EF-E1 | H14: Mechanical-first reclaim, waste-heat recovery, reduces S3 new-sand transport | J14: Auto Ancillary - Wiring Harness & Electricals
A15: 2. FORGING | J15: Auto Ancillary - Electronics & EV Components
A16: FG-01 | B16: Billet shearing / sawing | C16: Cutting steel bars into billets for forging — crankshafts, connecting rods, gears, axle beams. | D16: Electricity; steel bar stock | E16: Purchased electricity; upstream steel (S3) | F16: S2, S3 | G16: EF-E1, EF-S1 | H16: Yield optimisation, scrap segregation for recycling | J16: Auto Ancillary - Friction & Sintered Parts
A17: FG-02 | B17: Billet heating — fuel-fired furnace | C17: Heating billets to 1,100–1,250°C in FO/NG-fired furnaces before hot forging. | D17: Furnace oil / natural gas (30–60 litres FO per tonne typical) | E17: On-site fuel combustion — LARGEST S1 source in forge shops | F17: S1 | G17: EF-F2, EF-F5 | H17: Recuperative burners, NG conversion, furnace pressure control, hot charging | J17: Auto Ancillary - Seating, Trim & Interiors
A18: FG-03 | B18: Billet heating — induction | C18: Electric induction heating of billets (modern forge lines). | D18: Grid electricity (~350–450 kWh/t) | E18: Purchased electricity | F18: S2 | G18: EF-E1 | H18: Coil matching, RE power, standby-loss control | J18: Auto Ancillary - Glass & Glazing
A19: FG-04 | B19: Hot / warm forging (press or hammer) | C19: Deformation of heated billets in dies — crankshafts, stub axles, yokes, flanges, gear blanks. | D19: Electricity (press drives, compressors); die lube, graphite | E19: Purchased electricity | F19: S2 | G19: EF-E1 | H19: Servo presses, flash reduction (near-net forging), die-life management | J19: Auto Ancillary - Assemblies & Modules (Tier-1)
A20: FG-05 | B20: Cold forging / cold heading | C20: Room-temperature forming of fasteners, shafts, pins, spark-plug bodies. | D20: Electricity; steel wire/coil; phosphate-soap lube | E20: Purchased electricity; pre-treatment chemicals | F20: S2 | G20: EF-E1 | H20: High-speed headers, tool coatings, eliminating downstream machining | J20: Auto Ancillary - Multi-Process / Integrated
A21: FG-06 | B21: Ring rolling | C21: Seamless rolled rings for bearing races and gears. | D21: Electricity; billet heating fuel | E21: Fuel (S1) + electricity (S2) | F21: S1, S2 | G21: EF-F2, EF-F5, EF-E1 | H21: Near-net rolling, recuperators
A22: FG-07 | B22: Trimming, piercing & coining | C22: Removal of forging flash; sizing operations. | D22: Electricity | E22: Purchased electricity | F22: S2 | G22: EF-E1 | H22: Flashless/precision forging to eliminate step
A23: 3. MACHINING
A24: MC-01 | B24: CNC turning | C24: Turned shafts, hubs, bearing components, pulleys, fasteners. | D24: Electricity (spindles, hydraulics, coolant pumps); cutting oil/coolant | E24: Purchased electricity | F24: S2 | G24: EF-E1 | H24: Idle-time shutdown, high-efficiency spindles, optimised cutting parameters, MQL
A25: MC-02 | B25: Milling / machining centres (VMC/HMC) | C25: Prismatic machining of housings, brackets, heads, blocks. | D25: Electricity; tooling, coolant | E25: Purchased electricity | F25: S2 | G25: EF-E1 | H25: Fixture/multi-op consolidation, machine monitoring (GF360 IoT), RE power
A26: MC-03 | B26: Drilling, tapping & boring | C26: Hole-making and threading operations across components. | D26: Electricity | E26: Purchased electricity | F26: S2 | G26: EF-E1 | H26: Combined tooling, process consolidation
A27: MC-04 | B27: Grinding (surface / cylindrical / centreless) | C27: Precision finishing of shafts, races, valves, cam/crank journals. | D27: Electricity (high specific energy); grinding wheels, coolant | E27: Purchased electricity | F27: S2 | G27: EF-E1 | H27: Dressing optimisation, superabrasive (CBN) wheels, coolant pump VFDs
A28: MC-05 | B28: Honing / lapping / superfinishing | C28: Bore finishing (cylinder liners, con rods), gear tooth finishing. | D28: Electricity; honing oil, abrasives | E28: Purchased electricity | F28: S2 | G28: EF-E1 | H28: Process parameter optimisation
A29: MC-06 | B29: Gear cutting (hobbing / shaping / shaving / grinding) | C29: Transmission gears, differential gears, sprockets, steering pinions. | D29: Electricity; hobs & cutters, cutting oil | E29: Purchased electricity | F29: S2 | G29: EF-E1 | H29: Dry/hard hobbing, skiving, tool coatings
A30: MC-07 | B30: Broaching | C30: Internal splines, keyways in hubs, gears, yokes. | D30: Electricity | E30: Purchased electricity | F30: S2 | G30: EF-E1 | H30: Tooling life management
A31: MC-08 | B31: EDM / wire-cut (tool room) | C31: Die and mould making, tooling maintenance. | D31: Electricity; dielectric fluid, brass wire | E31: Purchased electricity | F31: S2 | G31: EF-E1 | H31: Generator efficiency modes
A32: MC-09 | B32: Coolant, chip & oil-mist management | C32: Coolant circulation/filtration, chip conveyors, mist extraction. | D32: Electricity; coolants & additives (S3); waste oil disposal (S3) | E32: Purchased electricity; waste treatment (S3) | F32: S2, S3 | G32: EF-E1 | H32: Centralised coolant systems, chip briquetting (better scrap value & lower transport)
A33: 4. SHEET METAL, STAMPING & FABRICATION
A34: SM-01 | B34: Coil slitting / decoiling / blanking | C34: Preparation of steel/Al coil into blanks — body panels, brackets. | D34: Electricity; steel/Al coil (S3, CBAM-relevant input) | E34: Purchased electricity; upstream metal (S3) | F34: S2, S3 | G34: EF-E1, EF-S1, EF-S3 | H34: Nesting/yield optimisation (directly cuts S3), scrap segregation
A35: SM-02 | B35: Press stamping / deep drawing | C35: Mechanical/hydraulic/servo presses — panels, cross members, wheel discs, fuel-tank halves. | D35: Electricity (press drives, compressed air); drawing lube | E35: Purchased electricity | F35: S2 | G35: EF-E1 | H35: Servo press retrofits, die cushion energy recovery, compressed-air leak control
A36: SM-03 | B36: Fine blanking | C36: High-precision flat parts — seat recliner plates, gears, levers. | D36: Electricity | E36: Purchased electricity | F36: S2 | G36: EF-E1 | H36: Tool life & material utilisation
A37: SM-04 | B37: Roll forming / ERW tube mills | C37: Formed sections and welded tubes — door beams, exhaust tubes, chassis members. | D37: Electricity (mill drives, HF welder) | E37: Purchased electricity | F37: S2 | G37: EF-E1 | H37: HF welder efficiency, line speed optimisation
A38: SM-05 | B38: Tube bending & end forming | C38: Exhaust systems, fuel/brake lines, chassis and seat tubes. | D38: Electricity; mandrel lube | E38: Purchased electricity | F38: S2 | G38: EF-E1 | H38: CNC benders, right-first-time quality
A39: SM-06 | B39: Laser / plasma / waterjet cutting | C39: Profile cutting of sheets and tubes; prototyping and low-volume parts. | D39: Electricity; assist gases (N2, O2); plasma gas | E39: Purchased electricity; minor process gases | F39: S2 | G39: EF-E1 | H39: Fiber laser upgrades (vs CO2 laser), nesting software
A40: SM-07 | B40: CNC press brake bending | C40: Bent brackets, enclosures, battery trays. | D40: Electricity | E40: Purchased electricity | F40: S2 | G40: EF-E1 | H40: Electric (servo) press brakes
A41: 5. JOINING & WELDING
A42: JW-01 | B42: MIG / MAG welding | C42: Structural welding of frames, axles, exhausts, seat structures, BIW sub-assemblies. | D42: Electricity; CO2 / Ar-CO2 shielding gas; wire | E42: Electricity (S2); CO2 shielding gas released (S1); weld wire (S3) | F42: S1, S2 | G42: EF-E1, EF-R6 | H42: Inverter power sources, gas-saver kits, weld-length optimisation, robotic welding
A43: JW-02 | B43: TIG welding | C43: Precision welding — SS exhaust parts, Al components, fuel rails. | D43: Electricity; argon | E43: Purchased electricity | F43: S2 | G43: EF-E1 | H43: Inverter sources, automation
A44: JW-03 | B44: Resistance spot / seam / projection welding | C44: Sheet-metal joining — panels, nuts/studs, fuel tanks, seat frames. | D44: Electricity (high peak demand); cooling water | E44: Purchased electricity | F44: S2 | G44: EF-E1 | H44: MFDC (mid-frequency DC) guns, demand management
A45: JW-04 | B45: Brazing (furnace / induction / flame) | C45: Heat exchangers (radiators, condensers, oil coolers), carbide tipping. | D45: NG/LPG (flame, CAB furnaces) or electricity (induction); flux, filler | E45: Fuel combustion (S1); electricity (S2) | F45: S1, S2 | G45: EF-F5, EF-F4, EF-E1 | H45: CAB furnace insulation & nitrogen management, induction conversion
A46: JW-05 | B46: Soldering (radiators, electricals, electronics) | C46: Joining copper/brass cores; PCB wave/selective soldering. | D46: Electricity; solder alloys, flux | E46: Purchased electricity | F46: S2 | G46: EF-E1 | H46: Lead-free reflow profile optimisation
A47: JW-06 | B47: Friction / friction-stir / laser welding | C47: Propeller shafts, axle tubes, EV battery trays (Al), gear clusters. | D47: Electricity | E47: Purchased electricity | F47: S2 | G47: EF-E1 | H47: Replaces fuel-based processes — inherently efficient; cycle optimisation
A48: JW-07 | B48: Riveting, clinching & adhesive bonding | C48: Mechanical joining and structural adhesives — mixed-material assemblies. | D48: Electricity (minor); adhesives, rivets (S3) | E48: Minor electricity; upstream consumables (S3) | F48: S2, S3 | G48: EF-E1 | H48: Low-cure-temperature adhesives
A49: 6. HEAT TREATMENT
A50: HT-01 | B50: Carburising / carbonitriding | C50: Case hardening of gears, shafts, bearings in sealed-quench/continuous furnaces with endothermic atmosphere. | D50: NG/LPG (furnace + endo-gas generator from LPG/methanol); electricity | E50: Fuel combustion + cracked endo gas (S1) — MAJOR hotspot; electricity (S2) | F50: S1, S2 | G50: EF-F5, EF-F4, EF-E1 | H50: Low-pressure (vacuum) carburising, endo-gas generator tuning, furnace insulation, waste-heat recovery
A51: HT-02 | B51: Hardening, quenching & tempering | C51: Through-hardening of fasteners, springs, axle parts; oil/polymer/salt quench. | D51: NG/LPG/FO or electricity; quench oil | E51: Fuel (S1) / electricity (S2); quench-oil top-up (S3) | F51: S1, S2 | G51: EF-F5, EF-F4, EF-F2, EF-E1 | H51: Continuous furnace loading optimisation, electric conversion, quench-oil life extension
A52: HT-03 | B52: Annealing / normalising / stress relieving | C52: Softening & microstructure control of forgings, castings, cold-formed parts. | D52: NG/LPG/FO or electricity | E52: Fuel (S1) / electricity (S2) | F52: S1, S2 | G52: EF-F5, EF-F4, EF-F2, EF-E1 | H52: Batch consolidation, insulation upgrades, scheduling
A53: HT-04 | B53: Induction hardening & tempering | C53: Localised hardening — crank journals, CV joints, gear teeth, axle shafts. | D53: Grid electricity (high power, short cycle) | E53: Purchased electricity | F53: S2 | G53: EF-E1 | H53: Energy-per-piece monitoring (GF360 IoT), coil design, RE power
A54: HT-05 | B54: Nitriding / gas nitrocarburising | C54: Surface hardening of crankshafts, valves, dies using NH3-based atmospheres. | D54: Electricity; ammonia, N2, CO2 process gases | E54: Electricity (S2); N2O traces possible (minor); process gas (S3) | F54: S1, S2 | G54: EF-E1 | H54: Plasma (ion) nitriding conversion, atmosphere control
A55: HT-06 | B55: Solution treatment & ageing (aluminium) | C55: T6/T7 treatment of Al castings — heads, wheels, suspension parts. | D55: Electricity or NG furnaces | E55: Fuel (S1) / electricity (S2) | F55: S1, S2 | G55: EF-F5, EF-E1 | H55: Furnace load density, air-quench where feasible
A56: HT-07 | B56: Shot peening | C56: Fatigue-life enhancement of springs, gears, con rods. | D56: Electricity; shot media | E56: Purchased electricity | F56: S2 | G56: EF-E1 | H56: Media management, process control
A57: 7. SURFACE TREATMENT & COATING
A58: ST-01 | B58: Degreasing & pre-treatment | C58: Alkaline cleaning, phosphating / zirconium conversion coating before paint/plating. | D58: Electricity; steam or electric bath heating; chemicals; water | E58: Bath-heating fuel (S1) / electricity (S2); chemicals & water (S3); effluent to ETP | F58: S1, S2, S3 | G58: EF-F5, EF-E1 | H58: Low-temperature chemistries, bath insulation & covers, counter-flow rinsing, heat pumps
A59: ST-02 | B59: Pickling (acid) | C59: Scale removal from forgings/wires before drawing or plating. | D59: Electricity; acid (HCl/H2SO4); neutralisation chemicals | E59: Electricity; chemical supply chain (S3); effluent | F59: S2, S3 | G59: EF-E1 | H59: Acid recovery/regeneration, mechanical descaling
A60: ST-03 | B60: Electroplating (Zn, Zn-Ni, hard Cr, Ni) | C60: Corrosion/wear coating of fasteners, brake parts, shafts, trim. | D60: Electricity (rectifiers, bath heating); anodes & chemistry; water | E60: Purchased electricity — rectifiers & heating; zinc/nickel anodes (S3) | F60: S2, S3 | G60: EF-E1, EF-S6 | H60: High-efficiency rectifiers (IGBT), bath temperature control, trivalent chemistry, drag-out reduction
A61: ST-04 | B61: Anodising (aluminium) | C61: Decorative/hard anodising of Al trim and pistons. | D61: Electricity (rectifiers, chillers); acid electrolyte | E61: Purchased electricity | F61: S2 | G61: EF-E1 | H61: Rectifier efficiency, heat recovery from electrolyte cooling
A62: ST-05 | B62: CED / e-coating (cathodic electro-deposition) | C62: Primer coat for BIW parts, chassis components, wheels. | D62: Electricity (bath, rectifier, RO/DM water); NG/LPG curing ovens | E62: Curing-oven fuel (S1) — hotspot; electricity (S2) | F62: S1, S2 | G62: EF-F5, EF-F4, EF-E1 | H62: Oven insulation & air-seal, RTO heat recovery, bake-window optimisation
A63: ST-06 | B63: Powder coating | C63: Decorative/protective coating of wheels, frames, small parts. | D63: Electricity (booth, cure oven) or NG/LPG ovens; powder | E63: Cure-oven fuel (S1) / electricity (S2); powder overspray (S3) | F63: S1, S2 | G63: EF-F5, EF-F4, EF-E1 | H63: Low-cure powders, powder reclaim, IR/hybrid ovens
A64: ST-07 | B64: Liquid painting line | C64: Topcoat/clear coat for plastic & metal parts — bumpers, mirrors, tanks. | D64: Electricity (booths, ASU); NG/LPG bake ovens; paints/solvents | E64: Oven & RTO fuel (S1); electricity (S2); solvent VOCs (non-GHG but regulated) | F64: S1, S2 | G64: EF-F5, EF-F4, EF-E1 | H64: High-solids/waterborne paints, booth air recirculation, oven heat recovery
A65: ST-08 | B65: Hot-dip galvanising | C65: Zinc coating of chassis/structural parts, fasteners (after-fabrication). | D65: NG/FO-fired zinc kettle; zinc metal; flux | E65: Kettle fuel combustion (S1) — hotspot; zinc (S3) | F65: S1, S3 | G65: EF-F5, EF-F2, EF-S6 | H65: Kettle insulation, dross/ash minimisation, zinc-thickness control
A66: ST-09 | B66: PVD / CVD / DLC coating | C66: Thin-film coating of piston rings, tappets, tooling. | D66: Electricity (vacuum systems, power supplies); process gases | E66: Purchased electricity | F66: S2 | G66: EF-E1 | H66: Batch loading optimisation
A67: ST-10 | B67: Passivation, sealing & rust preventives | C67: Final corrosion protection and packaging oils. | D67: Electricity (minor); chemicals & oils (S3) | E67: Minor electricity; consumables (S3) | F67: S2, S3 | G67: EF-E1 | H67: Water-based RP oils, dosing control
A68: 8. PLASTICS & POLYMER PROCESSING
A69: PL-01 | B69: Resin drying & material handling | C69: Drying of PA/ABS/PC granules before moulding. | D69: Electricity (dehumidifying dryers, conveying) | E69: Purchased electricity | F69: S2 | G69: EF-E1 | H69: Dryer scheduling, dew-point control, central material handling
A70: PL-02 | B70: Injection moulding | C70: Interior/exterior trims, dashboards, fans, tanks, connectors, lamp housings. | D70: Electricity (hydraulic 1.0–1.5 kWh/kg; all-electric 0.4–0.7 kWh/kg); polymer resins (S3) | E70: Purchased electricity — machines, chillers, dryers; resin (S3) | F70: S2, S3 | G70: EF-E1, EF-S7 | H70: All-electric/hybrid machines, barrel insulation jackets, regrind usage, chiller optimisation
A71: PL-03 | B71: Blow moulding | C71: Fuel tanks (HDPE), air ducts, washer bottles. | D71: Electricity; HDPE resin | E71: Purchased electricity; resin (S3) | F71: S2, S3 | G71: EF-E1, EF-S7 | H71: Accumulator-head efficiency, lightweighting
A72: PL-04 | B72: Extrusion (profiles & tubing) | C72: Weather strips, fuel/brake tubing, cable conduits. | D72: Electricity; PVC/TPE/PA resins | E72: Purchased electricity; resin (S3) | F72: S2, S3 | G72: EF-E1, EF-S7 | H72: Direct-drive extruders, die optimisation
A73: PL-05 | B73: Thermoforming / vacuum forming | C73: Trunk liners, door trims, underbody covers. | D73: Electricity (IR heaters, vacuum) | E73: Purchased electricity | F73: S2 | G73: EF-E1 | H73: Zoned IR heating, sheet-gauge optimisation
A74: PL-06 | B74: PU foam moulding | C74: Seat cushions, NVH foams, headrests, steering-wheel skins. | D74: Electricity; polyol/isocyanate (S3); mould heating (electric/water) | E74: Electricity (S2); chemical precursors (S3); blowing agents (check GWP) | F74: S1, S2, S3 | G74: EF-E1, EF-R1 | H74: Water-blown (zero-GWP) formulations, mould-carrier efficiency, bio-polyols
A75: PL-07 | B75: Painting / metallising of plastic parts | C75: Decorative finishes on grilles, logos, wheel covers. | D75: Electricity (booths, vacuum metallising); paints | E75: Electricity; oven fuel if fired (S1); VOCs | F75: S1, S2 | G75: EF-E1, EF-F4 | H75: UV-cure coatings, film/IMD alternatives
A76: PL-08 | B76: Ultrasonic / vibration / hot-plate welding | C76: Joining of lamps, tanks, air-intake manifolds. | D76: Electricity | E76: Purchased electricity | F76: S2 | G76: EF-E1 | H76: Servo-driven weld heads
A77: 9. RUBBER & ELASTOMERS
A78: RB-01 | B78: Rubber mixing / compounding | C78: Banbury/kneader + mill mixing of polymer, carbon black, oils — for all rubber parts. | D78: Electricity (very energy-intensive); polymers, carbon black (high-S3) | E78: Purchased electricity — mixing drives & cooling; carbon black (S3) | F78: S2, S3 | G78: EF-E1, EF-S8 | H78: Upside-down mixing, temperature control, sourcing low-carbon carbon black
A79: RB-02 | B79: Calendering & extrusion (rubber) | C79: Sheeting, profiles, hose tubes, tread/preforms. | D79: Electricity; steam (boiler) | E79: Electricity (S2); boiler fuel (S1) | F79: S1, S2 | G79: EF-E1, EF-F2, EF-F5 | H79: Extruder drive efficiency, steam-trap management
A80: RB-03 | B80: Moulding (compression / transfer / injection) | C80: Engine mounts, bushes, seals, gaskets, boots, grommets. | D80: Electricity (press heating platens) or steam | E80: Electricity (S2) / boiler fuel (S1) | F80: S1, S2 | G80: EF-E1, EF-F2 | H80: Electric platen heating with insulation, cure-time optimisation (cold runner)
A81: RB-04 | B81: Vulcanisation / curing (autoclave, salt bath, ovens) | C81: Curing of hoses, weather strips, belts. | D81: Steam from FO/briquette boilers; electricity; N2 | E81: Boiler fuel combustion (S1) — hotspot; electricity (S2) | F81: S1, S2 | G81: EF-F2, EF-F8, EF-E1 | H81: Biomass-briquette boilers (biogenic), condensate recovery, microwave/UHF curing
A82: RB-05 | B82: Rubber-to-metal bonding | C82: Bonded anti-vibration parts — mounts, bushes; includes metal prep & adhesives. | D82: Electricity; phosphating; bonding agents | E82: Electricity; chemical inputs (S3) | F82: S2, S3 | G82: EF-E1 | H82: Adhesive dosing control, integrated pre-treatment
A83: RB-06 | B83: Hose braiding & assembly | C83: Braided fuel/brake/coolant hoses with fittings. | D83: Electricity | E83: Purchased electricity | F83: S2 | G83: EF-E1 | H83: Machine efficiency
A84: 10. ELECTRICAL, ELECTRONICS & EV COMPONENTS
A85: EE-01 | B85: Wiring harness manufacture | C85: Wire cutting, crimping, taping, board assembly — full vehicle harnesses. | D85: Electricity (low intensity, labour-led); copper wire, PVC (high-S3) | E85: Purchased electricity; copper & PVC upstream (S3 dominant) | F85: S2, S3 | G85: EF-E1, EF-S5 | H85: LED lighting & HVAC efficiency (labour halls), copper scrap recovery, supplier engagement on Cu
A86: EE-02 | B86: PCB assembly (SMT + wave/selective solder) | C86: ECUs, sensors, clusters, BMS boards, chargers. | D86: Electricity (reflow ovens, AOI, HVAC/cleanroom); PCBs & components (S3) | E86: Purchased electricity; electronics upstream (S3 dominant) | F86: S2, S3 | G86: EF-E1 | H86: Reflow-oven N2 & energy optimisation, HVAC setpoint control
A87: EE-03 | B87: Motor winding & varnishing | C87: Starter motors, alternators, wiper/window motors, EV traction motors. | D87: Electricity (winding, varnish bake ovens); copper wire, e-steel (S3) | E87: Electricity (S2); varnish-oven fuel if fired (S1); Cu & electrical steel (S3) | F87: S1, S2, S3 | G87: EF-E1, EF-S5, EF-S1 | H87: Trickle-impregnation (less varnish energy), high-fill winding, e-steel scrap control
A88: EE-04 | B88: EV battery module & pack assembly | C88: Cell testing, module stacking, laser welding, BMS integration, end-of-line test. | D88: Electricity (dry room, laser welders, cyclers/testers); cells (very high S3) | E88: Purchased electricity — dry-room HVAC dominant; cell upstream (S3 dominant) | F88: S2, S3 | G88: EF-E1 | H88: Dry-room dehumidification efficiency, regenerative cell cyclers, low-carbon cell sourcing
A89: EE-05 | B89: Sensor / actuator / ECU assembly & calibration | C89: ABS/airbag sensors, throttle bodies, actuators, controllers. | D89: Electricity (assembly, environmental test chambers) | E89: Purchased electricity | F89: S2 | G89: EF-E1 | H89: Test-chamber scheduling & insulation
A90: EE-06 | B90: Automotive lighting assembly | C90: Head/tail lamps, LED modules — moulding, metallising, assembly, photometry. | D90: Electricity (metallising vacuum, photometric test) | E90: Purchased electricity | F90: S2 | G90: EF-E1 | H90: Vacuum-system efficiency, LED photometric test time reduction
A91: EE-07 | B91: Magnet & rotor assembly (EV) | C91: Magnet insertion, rotor balancing for traction motors. | D91: Electricity; NdFeB magnets (high-S3) | E91: Electricity; rare-earth magnet upstream (S3) | F91: S2, S3 | G91: EF-E1 | H91: Magnet recycling programmes, supplier data via GF360 portal
A92: 11. FRICTION, SINTERED & COMPOSITE PARTS
A93: FS-01 | B93: Powder metallurgy — pressing & sintering | C93: Sintered gears, sprockets, bushes, VVT parts; belt/mesh furnaces with endo/N2-H2 atmosphere. | D93: Electricity + NG/LPG sintering furnaces (1,100–1,150°C); metal powders (S3) | E93: Furnace fuel & cracked atmosphere (S1); electricity (S2) — hotspot | F93: S1, S2, S3 | G93: EF-F5, EF-F4, EF-E1 | H93: Furnace muffle insulation, atmosphere flow optimisation, warm compaction
A94: FS-02 | B94: Brake pad / lining manufacture | C94: Mixing, hot pressing, curing, scorching, grinding of friction material. | D94: Electricity (hot presses, curing ovens, scorching); resins, fibres (S3) | E94: Electricity (S2); oven fuel if fired (S1); phenolic resin (S3) | F94: S1, S2, S3 | G94: EF-E1, EF-F4 | H94: Press platen insulation, cure-cycle optimisation, Cu-free formulations
A95: FS-03 | B95: Clutch facing & disc manufacture | C95: Winding/moulding, curing, machining of clutch facings and discs. | D95: Electricity; resin curing ovens | E95: Electricity (S2); oven fuel (S1) | F95: S1, S2 | G95: EF-E1, EF-F4 | H95: Oven batch optimisation
A96: FS-04 | B96: Composite moulding (SMC / GMT / CFRP) | C96: Lightweight panels, battery covers, leaf springs, underbody shields. | D96: Electricity (heated presses, ovens); resin & glass/carbon fibre (S3) | E96: Electricity (S2); fibre & resin upstream (S3) | F96: S2, S3 | G96: EF-E1 | H96: Fast-cure resins, press heat recovery, recycled fibre
A97: 12. GLASS, SEATING & INTERIOR TRIM
A98: GT-01 | B98: Auto glass processing | C98: Cutting, tempering (roller-hearth furnace), bending, lamination of windshields/windows. | D98: Electricity + NG (tempering/bending furnaces); float glass (S3) | E98: Furnace fuel (S1) / electricity (S2) — hotspot; float glass upstream (S3) | F98: S1, S2, S3 | G98: EF-F5, EF-E1, EF-S10 | H98: Furnace convection upgrades, load optimisation, glass cullet recycling
A99: GT-02 | B99: Seat manufacture | C99: Frame welding, PU foam pads, trim covers, assembly to complete seats. | D99: Electricity; PU chemicals, fabrics/leather, steel frames (S3) | E99: Electricity (S2); upstream materials (S3 dominant) | F99: S2, S3 | G99: EF-E1, EF-S1 | H99: Foam yield, frame lightweighting, fabric offcut recycling
A100: GT-03 | B100: Interior trim & dashboard manufacture | C100: Injection moulding, skin forming, IP assembly, door panels, consoles. | D100: Electricity; polymers, foils (S3) | E100: Electricity (S2); polymer upstream (S3) | F100: S2, S3 | G100: EF-E1, EF-S7 | H100: Slush-moulding energy control, recycled-content polymers
...

Sheet Emission Factors (India)
A1: DEFAULT EMISSION FACTORS — INDIA
A2: India-specific default emission factors for the auto ancillary / manufacturing sector. All factor values are BLUE editable defaults on yellow — verify against the latest CEA database, IPCC guidelines and supplier data at proposal time. kgCO2e per unit basis unless stated. Material factors are indicative cradle-to-gate values and vary widely by route and supplier.
A3: Code | B3: Category | C3: Source / Activity | D3: Unit | E3: EF (kgCO2e per unit) | F3: Alternative basis | G3: Scope | H3: Source / Rationale
A4: A. GRID ELECTRICITY (SCOPE 2)
A5: EF-E1 | B5: Electricity | C5: Grid electricity — all-India weighted average (incl. renewables) | D5: kWh | E5: 0.7117 | F5: 0.7117 tCO2/MWh | G5: S2 | H5: CEA CO2 Baseline Database, Version 21.0 (Nov 2025), FY 2024-25 weighted average emission factor. Standard location-based Scope 2 factor for India under the GHG Protocol. Update annually when CEA releases a new version.
A6: EF-E2 | B6: Electricity | C6: Grid electricity — combined margin (CDM / offset projects) | D6: kWh | E6: 0.7383 | F6: 0.7383 tCO2/MWh | G6: S2 | H6: CEA CO2 Baseline Database v21.0 (Nov 2025) combined margin — use only for CDM/carbon-credit baseline calculations, not for corporate Scope 2 inventory.
A7: EF-E3 | B7: Electricity | C7: On-site solar PV / contracted renewable power | D7: kWh | E7: 0 | F7: 0 tCO2/MWh (generation) | G7: S2 | H7: Zero operational emissions at generation. Under market-based Scope 2 accounting, renewable purchases with RECs/green tariffs are reported at 0; embodied panel emissions sit in Scope 3.
A8: B. STATIONARY COMBUSTION — FUELS (SCOPE 1)
A9: EF-F1 | B9: Fuel | C9: High-speed diesel (HSD) — DG sets, burners | D9: litre | E9: 2.68 | F9: 74.1 tCO2/TJ (NCV) | G9: S1 | H9: IPCC 2006 Guidelines Vol.2 default (gas/diesel oil) with Indian density and NCV; consistent with India GHG Program (WRI India / CII / TERI) published factor of ~2.68 kgCO2/litre.
A10: EF-F2 | B10: Fuel | C10: Furnace oil (FO) — furnaces, boilers, thermic fluid heaters | D10: kg | E10: 3.13 | F10: 77.4 tCO2/TJ (NCV) | G10: S1 | H10: IPCC 2006 default (residual fuel oil), NCV ~40.4 MJ/kg. Approx. 3.0 kgCO2 per litre at 0.95 kg/l density.
A11: EF-F3 | B11: Fuel | C11: Light diesel oil (LDO) | D11: litre | E11: 2.71 | F11: 74.1 tCO2/TJ (NCV) | G11: S1 | H11: IPCC 2006 default (gas/diesel oil basket) with Indian LDO density/NCV.
A12: EF-F4 | B12: Fuel | C12: LPG — furnaces, brazing, ovens, canteen | D12: kg | E12: 2.98 | F12: 63.1 tCO2/TJ (NCV) | G12: S1 | H12: IPCC 2006 default, NCV ~47.3 MJ/kg. Approx. 1.6 kgCO2 per litre of liquid LPG.
A13: EF-F5 | B13: Fuel | C13: Natural gas / PNG — furnaces, ovens, kettles | D13: SCM | E13: 1.95 | F13: 56.1 tCO2/TJ (NCV) | G13: S1 | H13: IPCC 2006 default with typical Indian pipeline gas NCV of ~34.9 MJ/SCM (GCV ~38.7 MJ/SCM). Verify against the GA/supplier's gas quality certificate.
A14: EF-F6 | B14: Fuel | C14: Coal — Indian non-coking (boiler grade) | D14: tonne | E14: 1580 | F14: ~96 tCO2/TJ (NCV) | G14: S1 | H14: Indicative for Indian non-coking coal of GCV ~4,000 kcal/kg (CEA/CIMFR basis). Highly GCV-dependent (1.4–2.2 tCO2/t across grades) — always use the grade-specific GCV and carbon content from the coal supplier.
A15: EF-F7 | B15: Fuel | C15: Foundry / met coke (cupola) | D15: tonne | E15: 3020 | F15: 107 tCO2/TJ (NCV) | G15: S1 | H15: IPCC 2006 default for coke oven coke, NCV ~28.2 MJ/kg.
A16: EF-F8 | B16: Fuel | C16: Biomass briquettes / agro-waste (boilers) | D16: tonne | E16: 0 | F16: Biogenic CO2 ~1,500 kg/t reported separately | G16: S1 | H16: Fossil CO2 counted as zero under GHG Protocol; biogenic CO2 reported outside the scopes. Minor CH4/N2O from combustion (~10–30 kgCO2e/t) may be added for completeness per IPCC defaults.
A17: EF-F9 | B17: Fuel | C17: Petrol / motor spirit (MS) | D17: litre | E17: 2.27 | F17: 69.3 tCO2/TJ (NCV) | G17: S1 | H17: IPCC 2006 default (motor gasoline) with Indian density ~0.74 kg/l.
A18: EF-F10 | B18: Process gas | C18: Acetylene (gas cutting / flame processes) | D18: kg | E18: 3.38 | F18: Stoichiometric | G18: S1 | H18: Stoichiometric combustion of C2H2 (88 g CO2 per 26 g C2H2).
A19: C. MOBILE COMBUSTION — VEHICLES & MATERIAL HANDLING (SCOPE 1)
A20: EF-M1 | B20: Mobile | C20: Diesel — company vehicles, forklifts, cranes | D20: litre | E20: 2.68 | F20: — | G20: S1 | H20: Same fuel basis as EF-F1; India GHG Program mobile combustion factor.
A21: EF-M2 | B21: Mobile | C21: Petrol — company vehicles, 2-wheelers, test fuel | D21: litre | E21: 2.27 | F21: — | G21: S1 | H21: Same fuel basis as EF-F9.
A22: EF-M3 | B22: Mobile | C22: CNG — company vehicles / shuttle buses | D22: kg | E22: 2.69 | F22: 56.1 tCO2/TJ (NCV) | G22: S1 | H22: IPCC 2006 natural gas default, NCV ~48 MJ/kg for CNG.
A23: EF-M4 | B23: Mobile | C23: LPG — forklifts | D23: kg | E23: 2.98 | F23: — | G23: S1 | H23: Same basis as EF-F4.
A24: D. REFRIGERANT & PROCESS-GAS FUGITIVES — GWP-100 (SCOPE 1)
A25: EF-R1 | B25: Refrigerant | C25: R-134a (vehicle AC charging lines, chillers) | D25: kg refrigerant | E25: 1300 | F25: GWP-100 (AR5) | G25: S1 | H25: IPCC AR5 100-year GWP. Emission = annual top-up / charge loss (kg) x GWP. Use AR6 value (1,530) if the client reports under latest BRSR Core / ISO 14064 guidance.
A26: EF-R2 | B26: Refrigerant | C26: R-410A (HVAC / chillers) | D26: kg refrigerant | E26: 1924 | F26: GWP-100 (AR5) | G26: S1 | H26: IPCC AR5 blend-weighted GWP (50% R-32 / 50% R-125).
A27: EF-R3 | B27: Refrigerant | C27: R-32 (new low-GWP HVAC) | D27: kg refrigerant | E27: 677 | F27: GWP-100 (AR5) | G27: S1 | H27: IPCC AR5. Preferred replacement gas in decarbonisation roadmaps.
A28: EF-R4 | B28: Refrigerant | C28: R-404A (cold storage / process chillers) | D28: kg refrigerant | E28: 3943 | F28: GWP-100 (AR5) | G28: S1 | H28: IPCC AR5 blend-weighted GWP — very high; prioritise phase-out.
A29: EF-R5 | B29: Refrigerant | C29: R-22 / HCFC-22 (legacy plants; being phased out under HPMP) | D29: kg refrigerant | E29: 1760 | F29: GWP-100 (AR5) | G29: S1 | H29: IPCC AR5. Also an ozone-depleting substance under India's HCFC Phase-out Management Plan — flag for replacement.
A30: EF-R6 | B30: Process gas | C30: CO2 — welding shielding gas (MIG/MAG), purchased CO2 | D30: kg gas | E30: 1 | F30: — | G30: S1 | H30: Purchased CO2 released to atmosphere is reported at GWP 1 (direct emission of the gas itself).
A31: EF-R7 | B31: Process gas | C31: SF6 (HV switchgear insulation) | D31: kg gas | E31: 23500 | F31: GWP-100 (AR5) | G31: S1 | H31: IPCC AR5. Tiny leaks dominate — maintain switchgear gas logs.
A32: E. PURCHASED MATERIALS — EMBODIED, CRADLE-TO-GATE (SCOPE 3 CAT 1; CBAM-RELEVANT)
A33: EF-S1 | B33: Material | C33: Steel — Indian primary (BF-BOF route) | D33: tonne | E33: 2550 | F33: 2.35–2.90 tCO2e/t range | G33: S3 | H33: Indicative Indian average (Ministry of Steel / worldsteel data: India averages ~2.5 tCO2/t crude steel vs global ~1.9 due to coal-based BF-BOF). CBAM-relevant input — replace with the mill's verified product footprint where available.
A34: EF-S2 | B34: Material | C34: Steel — secondary (scrap-EAF / induction furnace route) | D34: tonne | E34: 1200 | F34: 0.7–1.5 tCO2e/t range | G34: S3 | H34: Indicative for Indian scrap-based EAF/IF steel on grid power; global scrap-EAF benchmark ~0.7 tCO2/t. Strong lever: shifting to scrap-route steel typically halves the input footprint.
A35: EF-S3 | B35: Material | C35: Aluminium — Indian primary ingot | D35: tonne | E35: 18000 | F35: 16–21 tCO2e/t range | G35: S3 | H35: Indicative for Indian smelters on coal-based captive power (IAI regional data; global average ~11.5 tCO2e/t). Dominant footprint driver for Al-intensive components.
A36: EF-S4 | B36: Material | C36: Aluminium — recycled / secondary ingot | D36: tonne | E36: 800 | F36: 0.5–1.0 tCO2e/t range | G36: S3 | H36: ~95% lower than primary (IAI). Key lever for die-casters — maximise certified recycled content.
A37: EF-S5 | B37: Material | C37: Copper — refined (wire rod, windings) | D37: tonne | E37: 4000 | F37: 3.5–4.5 tCO2e/t range | G37: S3 | H37: Indicative global cradle-to-gate (ICA / ecoinvent-type sources); India-specific values depend on ore vs scrap route.
A38: EF-S6 | B38: Material | C38: Zinc — refined (galvanising / plating) | D38: tonne | E38: 3000 | F38: 2.5–4.0 tCO2e/t range | G38: S3 | H38: Indicative cradle-to-gate (IZA); primary Indian producer (hydrometallurgical) publishes lower product-specific values — use supplier EPD where available.
A39: EF-S7 | B39: Material | C39: Polymers — commodity/engineering average (PP, ABS, PA) | D39: tonne | E39: 2500 | F39: 1.6–6.5 tCO2e/t by resin | G39: S3 | H39: Indicative virgin-resin cradle-to-gate (PlasticsEurope-type data: PP ~1.6, ABS ~3.1, PA66 up to ~6.5). Use resin-specific factors; recycled resin is typically 50–80% lower.
A40: EF-S8 | B40: Material | C40: Rubber — synthetic (SBR/EPDM) incl. carbon black | D40: tonne | E40: 2600 | F40: NR ~0.7 tCO2e/t | G40: S3 | H40: Indicative for synthetic elastomer compounds; natural rubber is far lower (biogenic). Carbon black alone ~2.4–3.0 tCO2e/t.
A41: EF-S9 | B41: Material | C41: Pig iron / foundry-grade iron units | D41: tonne | E41: 2000 | F41: 1.7–2.3 tCO2e/t range | G41: S3 | H41: Indicative for Indian blast-furnace pig iron; foundry returns and scrap charge reduce the effective input factor.
A42: EF-S10 | B42: Material | C42: Flat / float glass | D42: tonne | E42: 1200 | F42: 1.0–1.4 tCO2e/t range | G42: S3 | H42: Indicative cradle-to-gate for float glass (fuel + carbonate process emissions).
A43: F. TRANSPORT & LOGISTICS (SCOPE 3 CAT 4 & 9)
A44: EF-T1 | B44: Transport | C44: Road freight — HDV rigid/articulated (>12 t) | D44: tonne-km | E44: 0.07 | F44: kgCO2e per t-km | G44: S3 | H44: Indicative India GHG Program road-freight factor for heavy-duty vehicles; varies with load factor and vehicle age.
A45: EF-T2 | B45: Transport | C45: Road freight — LCV / MDV (<12 t) | D45: tonne-km | E45: 0.25 | F45: kgCO2e per t-km | G45: S3 | H45: Indicative India GHG Program factor for light/medium commercial vehicles — much higher per t-km than HDVs; consolidate loads.
A46: EF-T3 | B46: Transport | C46: Rail freight (Indian Railways) | D46: tonne-km | E46: 0.01 | F46: ~10 gCO2 per NTKM | G46: S3 | H46: Indian Railways published net-tonne-km intensity (~9.7 gCO2/NTKM, falling as traction electrifies). Modal shift from road cuts freight emissions ~85%.
A47: EF-T4 | B47: Transport | C47: Sea freight — container (EU exports) | D47: tonne-km | E47: 0.012 | F47: kgCO2e per t-km | G47: S3 | H47: Indicative deep-sea container factor (GLEC/IMO-type averages) for India–EU export shipments.
A48: EF-T5 | B48: Transport | C48: Air freight (emergency shipments) | D48: tonne-km | E48: 0.6 | F48: kgCO2e per t-km | G48: S3 | H48: Indicative long-haul belly/freighter factor (GLEC-type average). ~50x sea freight — avoid via better planning.
A50: QUICK SCOPE 1+2 ESTIMATOR — DERIVE THE CLIENT'S EMISSIONS PROFILE FROM ACTIVITY DATA
A51: Enter the client's annual activity data (BLUE cells) collected during discovery. Emissions are computed from the default factors above (the tCO2e formulas pull live from column E — change a factor and the estimate updates). The resulting intensity can replace the placeholder 'Embedded Emissions Intensity' on the 'Client Inputs' tab.
B52: Energy source | C52: Annual quantity | D52: Unit | E52: EF used | F52: EF unit | G52: Scope | H52: tCO2e per year
B53: Grid electricity | C53: 3000 | D53: MWh | E53: =E5 -> 0.7117 | F53: tCO2/MWh | G53: S2 | H53: =C53*E5 -> 2135.1
B54: Diesel (DG sets + material handling) | C54: 40 | D54: kL | E54: =E9 -> 2.68 | F54: tCO2/kL | G54: S1 | H54: =C54*E9 -> 107.2
B55: Furnace oil | C55: 120 | D55: tonnes | E55: =E10 -> 3.13 | F55: tCO2/t | G55: S1 | H55: =C55*E10 -> 375.6
B56: Natural gas / PNG | C56: 0 | D56: '000 SCM | E56: =E13 -> 1.95 | F56: tCO2/'000 SCM | G56: S1 | H56: =C56*E13 -> 0
B57: LPG | C57: 60 | D57: tonnes | E57: =E12 -> 2.98 | F57: tCO2/t | G57: S1 | H57: =C57*E12 -> 178.8
B58: Coal (boiler grade) | C58: 0 | D58: tonnes | E58: =E14 -> 1580 | F58: kgCO2/t | G58: S1 | H58: =C58*E14/1000 -> 0
B59: Total Scope 1 — fuels (tCO2e) | H59: =SUM(H54:H58) -> 661.6
B60: Total Scope 2 — electricity (tCO2e) | H60: =H53 -> 2135.1
B61: TOTAL SCOPE 1 + 2 (tCO2e per year) | H61: =H59+H60 -> 2796.7
B63: Estimated emissions intensity (tCO2e per Rs Cr turnover) | H63: =H61/'Client Inputs'!$B$6 -> 11.1868
B64: Current model input — 'Embedded Emissions Intensity' on Client Inputs (for comparison) | H64: ='Client Inputs'!$B$13 -> 45
A66: If the estimator's intensity differs materially from the placeholder on 'Client Inputs' (B13), update B13 with this measured estimate — the CBAM exposure, cost-of-inaction and ROI results all flow from it. Note: intensity here is Scope 1+2 per Rs Cr of total turnover; CBAM embedded-emissions intensity is product-specific (per tonne of goods) and is refined in the GF360 platform.

Sheet Process Flow Diagrams
A1: PROCESS FLOW DIAGRAMS — AUTO ANCILLARY MANUFACTURING ROUTES
B2: Representative simplified flows for the main auto-ancillary process routes, annotated with energy inputs (amber boxes) and GHG emission scopes/hotspots (grey tags). S1 = on-site fuel/process emissions, S2 = purchased electricity, S3 = value chain. Map each client facility precisely in the GF360 platform during onboarding.
B3: Process step | D3: Energy / fuel input | F3: Scope tag / hotspot
B5: D1. GENERIC AUTO-ANCILLARY PLANT — END-TO-END VALUE FLOW
D6: Electricity + FO/NG/LPG | F6: Electricity | H6: NG/LPG/FO or electricity | J6: Electricity + NG/LPG ovens | L6: Electricity | P6: Diesel (3rd-party fleet)
D7: ↓ | F7: ↓ | H7: ↓ | J7: ↓ | L7: ↓ | P7: ↓
B8: Raw material receipt & storage | C8: → | D8: Primary forming (cast / forge / stamp / mould) | E8: → | F8: Machining & finishing | G8: → | H8: Heat treatment | I8: → | J8: Surface treatment & coating | K8: → | L8: Assembly & testing | M8: → | N8: Packaging | O8: → | P8: Dispatch & outbound logistics
B9: S3 — embodied materials (CBAM lever) | D9: S1+S2 HOTSPOT | F9: S2 | H9: S1+S2 HOTSPOT | J9: S1+S2 | L9: S2 | N9: S3 packaging | P9: S3 freight
B11: D2. FOUNDRY & CASTING ROUTE (FC-01 to FC-10)
D12: Electricity | F12: Electricity (induction) / coke (cupola) | H12: Electricity + resins | L12: Electricity + NG (thermal reclaim) | N12: Electricity | P12: FO/NG or electricity
D13: ↓ | F13: ↓ | H13: ↓ | L13: ↓ | N13: ↓ | P13: ↓
B14: Scrap / pig iron / ingot receipt | C14: → | D14: Charge preparation & weighing | E14: → | F14: Melting — induction or cupola | G14: → | H14: Moulding & core making | I14: → | J14: Pouring & solidification | K14: → | L14: Shakeout & sand reclamation | M14: → | N14: Fettling, grinding & shot blast | O14: → | P14: Heat treatment & inspection
B15: S3 — metallics | D15: S2 | F15: S2 or S1 — LARGEST hotspot (500-800 kWh/t melt) | H15: S2 | J15: — | L15: S1+S2 | N15: S2 | P15: S1+S2
B17: D3. FORGING & MACHINING ROUTE (FG-01 to FG-07, MC-01 to MC-09)
D18: Electricity | F18: FO/NG (furnace) or electricity (induction) | H18: Electricity | J18: Electricity | L18: NG/LPG or electricity | N18: Electricity
D19: ↓ | F19: ↓ | H19: ↓ | J19: ↓ | L19: ↓ | N19: ↓
B20: Steel bar / billet receipt | C20: → | D20: Billet cutting | E20: → | F20: Billet heating — furnace or induction | G20: → | H20: Forging press / hammer | I20: → | J20: Trimming & coining | K20: → | L20: Heat treatment (harden / temper) | M20: → | N20: Shot blast + CNC machining | O20: → | P20: Inspection & dispatch
B21: S3 — steel (CBAM-relevant) | D21: S2 | F21: S1 HOTSPOT (fuel) / S2 (induction) | H21: S2 | J21: S2 | L21: S1+S2 HOTSPOT | N21: S2 | P21: —
B23: D4. PRESS SHOP & FABRICATION ROUTE (SM-01 to SM-07, JW-01 to JW-07)
D24: Electricity | F24: Electricity + compressed air | H24: Electricity + assist gases | J24: Electricity + CO2/Ar shielding gas | L24: NG/LPG cure ovens + electricity | N24: Electricity
D25: ↓ | F25: ↓ | H25: ↓ | J25: ↓ | L25: ↓ | N25: ↓
B26: Steel / Al coil receipt | C26: → | D26: Slitting & blanking | E26: → | F26: Press stamping / deep drawing | G26: → | H26: Laser / plasma cutting | I26: → | J26: Welding — MIG / spot | K26: → | L26: Pre-treatment + e-coat / paint | M26: → | N26: Sub-assembly | O26: → | P26: Inspection & dispatch
B27: S3 — coil (CBAM lever) | D27: S2 (yield → S3) | F27: S2 | H27: S2 | J27: S1 (CO2 gas) + S2 | L27: S1+S2 HOTSPOT (ovens) | N27: S2 | P27: —
B29: D5. PLASTICS / POLYMER ROUTE (PL-01 to PL-08)
D30: Electricity (dryers) | F30: Electricity (machines + chillers) | H30: Electricity | J30: Electricity + NG/LPG ovens | L30: Electricity
D31: ↓ | F31: ↓ | H31: ↓ | J31: ↓ | L31: ↓
B32: Polymer granule receipt | C32: → | D32: Resin drying | E32: → | F32: Injection / blow moulding | G32: → | H32: Degating & trimming | I32: → | J32: Painting / metallising (optional) | K32: → | L32: Welding & assembly | M32: → | N32: Packing & dispatch
B33: S3 — resin (1.6-6.5 tCO2e/t) | D33: S2 | F33: S2 HOTSPOT (0.4-1.5 kWh/kg) | H33: S2 | J33: S1+S2 | L33: S2 | N33: S3 packaging & freight
B35: D6. SURFACE TREATMENT / PLATING LINE (ST-01 to ST-10)
D36: Steam / electric bath heating | F36: Electricity | H36: Electricity (rectifiers + heating) | J36: Electricity (pumps) | N36: NG/LPG or electricity
D37: ↓ | F37: ↓ | H37: ↓ | J37: ↓ | N37: ↓
B38: Component receipt | C38: → | D38: Degreasing / alkaline cleaning | E38: → | F38: Pickling / acid activation | G38: → | H38: Plating / phosphating / anodising baths | I38: → | J38: Rinse cascade (to ETP) | K38: → | L38: Passivation & sealing | M38: → | N38: Drying / curing oven | O38: → | P38: Inspection & dispatch
B39: — | D39: S1/S2 | F39: S2 | H39: S2 HOTSPOT (rectifiers); anodes → S3 | J39: S2 + ETP energy | L39: S3 chemicals | N39: S1+S2 | P39: —
B41: D7. RUBBER & ELASTOMER ROUTE (RB-01 to RB-06)
D42: Electricity (high) | F42: Electricity + steam | H42: Electricity / steam platens | J42: Steam — FO or biomass boiler | L42: Electricity
D43: ↓ | F43: ↓ | H43: ↓ | J43: ↓ | L43: ↓
B44: Polymer + carbon black receipt | C44: → | D44: Mixing / compounding (Banbury) | E44: → | F44: Calendering / extrusion / preforms | G44: → | H44: Moulding (compression / injection) | I44: → | J44: Vulcanisation / curing | K44: → | L44: Trimming & rubber-metal bonding | M44: → | N44: Testing & dispatch
B45: S3 — carbon black & polymer | D45: S2 HOTSPOT | F45: S1+S2 | H45: S1+S2 | J45: S1 HOTSPOT (boiler) — biomass lever | L45: S2 | N45: —
B47: These flows are simplified and representative — actual routings vary by plant. During GF360 onboarding each facility's process map is digitised, metered energy is mapped to process steps, and the hotspots above are quantified into the facility's marginal abatement cost curve (MACC).

Sheet Custom Process Flow
A1: CUSTOM PROCESS FLOW — BUILD THE CLIENT'S ROUTE STEP BY STEP
B2: Free-flow diagram builder: click any BLUE 'Select activity' cell and pick a process step from the dropdown (all 105 activities from the 'Auto Ancillary Activities' catalogue, coded by category). The scope, energy inputs, emission sources and decarbonisation levers for each chosen step fill in automatically below the box. Steps run 1→5 on the first band, continue 6→10 on the second; leave trailing steps blank for shorter routes. A forging-route example is pre-loaded — overwrite it with the client's actual sequence during discovery.
AA3: HELPER TABLE (do not edit) - feeds the step dropdowns and lookups
B4: STEP 1 | D4: STEP 2 | F4: STEP 3 | H4: STEP 4 | J4: STEP 5 | AA4: FC-01 - Induction furnace melting (iron / steel) | AB4: FC-01 | AC4: S2 | AD4: EF-E1 | AE4: Grid electricity (500–800 kWh/t melt); scrap, pig iron, ferroalloys | AF4: Purchased electricity for melting and holding | AG4: Melt scheduling & power factor, lid/insulation upgrades, RE power purchase, yield improvement
B5: FG-01 - Billet shearing / sawing | C5: → | D5: FG-02 - Billet heating — fuel-fired furnace | E5: → | F5: FG-04 - Hot / warm forging (press or hammer) | G5: → | H5: FG-07 - Trimming, piercing & coining | I5: → | J5: HT-02 - Hardening, quenching & tempering | AA5: FC-02 - Cupola furnace melting | AB5: FC-02 | AC5: S1 | AD5: EF-F7 | AE5: Foundry coke (~100–140 kg/t melt), limestone | AF5: On-site coke combustion | AG5: Divided-blast cupola, conversion to induction melting, waste-heat recovery
B6: =IF($B$5="","",IFERROR("Scope: "&VLOOKUP($B$5,$AA$4:$AG$108,3,FALSE)&" | EF: "&VLOOKUP($B$5,$AA$4:$AG$108,4,FALSE),"")) -> Scope: S2, S3 | EF: EF-E1, EF-S1 | D6: =IF($D$5="","",IFERROR("Scope: "&VLOOKUP($D$5,$AA$4:$AG$108,3,FALSE)&" | EF: "&VLOOKUP($D$5,$AA$4:$AG$108,4,FALSE),"")) -> Scope: S1 | EF: EF-F2, EF-F5 | F6: =IF($F$5="","",IFERROR("Scope: "&VLOOKUP($F$5,$AA$4:$AG$108,3,FALSE)&" | EF: "&VLOOKUP($F$5,$AA$4:$AG$108,4,FALSE),"")) -> Scope: S2 | EF: EF-E1 | H6: =IF($H$5="","",IFERROR("Scope: "&VLOOKUP($H$5,$AA$4:$AG$108,3,FALSE)&" | EF: "&VLOOKUP($H$5,$AA$4:$AG$108,4,FALSE),"")) -> Scope: S2 | EF: EF-E1 | J6: =IF($J$5="","",IFERROR("Scope: "&VLOOKUP($J$5,$AA$4:$AG$108,3,FALSE)&" | EF: "&VLOOKUP($J$5,$AA$4:$AG$108,4,FALSE),"")) -> Scope: S1, S2 | EF: EF-F5, EF-F4, EF-F2, EF-E1 | AA6: FC-03 - Aluminium melting & holding | AB6: FC-03 | AC6: S1, S2 | AD6: EF-F2, EF-F5, EF-F4, EF-E1 | AE6: FO / NG / LPG or electricity; Al ingot & scrap | AF6: Fuel combustion (S1) or electricity (S2); dross losses | AG6: Efficient tower furnaces, dross reduction, higher scrap (recycled Al) charge, electrification
B7: =IF($B$5="","",IFERROR("Inputs: "&VLOOKUP($B$5,$AA$4:$AG$108,5,FALSE),"")) -> Inputs: Electricity; steel bar stock | D7: =IF($D$5="","",IFERROR("Inputs: "&VLOOKUP($D$5,$AA$4:$AG$108,5,FALSE),"")) -> Inputs: Furnace oil / natural gas (30–60 litres FO per tonne typical) | F7: =IF($F$5="","",IFERROR("Inputs: "&VLOOKUP($F$5,$AA$4:$AG$108,5,FALSE),"")) -> Inputs: Electricity (press drives, compressors); die lube, graphite | H7: =IF($H$5="","",IFERROR("Inputs: "&VLOOKUP($H$5,$AA$4:$AG$108,5,FALSE),"")) -> Inputs: Electricity | J7: =IF($J$5="","",IFERROR("Inputs: "&VLOOKUP($J$5,$AA$4:$AG$108,5,FALSE),"")) -> Inputs: NG/LPG/FO or electricity; quench oil | AA7: FC-04 - High-pressure die casting (HPDC) | AB7: FC-04 | AC7: S1, S2 | AD7: EF-E1, EF-F4 | AE7: Electricity (machine, furnace holding); die lube, hydraulic oil | AF7: Purchased electricity; holding furnace fuel | AG7: Servo-hydraulic/toggle upgrades, holding furnace insulation, OEE improvement
B8: =IF($B$5="","",IFERROR("Emissions: "&VLOOKUP($B$5,$AA$4:$AG$108,6,FALSE),"")) -> Emissions: Purchased electricity; upstream steel (S3) | D8: =IF($D$5="","",IFERROR("Emissions: "&VLOOKUP($D$5,$AA$4:$AG$108,6,FALSE),"")) -> Emissions: On-site fuel combustion — LARGEST S1 source in forge shops | F8: =IF($F$5="","",IFERROR("Emissions: "&VLOOKUP($F$5,$AA$4:$AG$108,6,FALSE),"")) -> Emissions: Purchased electricity | H8: =IF($H$5="","",IFERROR("Emissions: "&VLOOKUP($H$5,$AA$4:$AG$108,6,FALSE),"")) -> Emissions: Purchased electricity | J8: =IF($J$5="","",IFERROR("Emissions: "&VLOOKUP($J$5,$AA$4:$AG$108,6,FALSE),"")) -> Emissions: Fuel (S1) / electricity (S2); quench-oil top-up (S3) | AA8: FC-05 - Gravity / low-pressure die casting | AB8: FC-05 | AC8: S1, S2 | AD8: EF-E1, EF-F5, EF-F4 | AE8: Electricity; NG/LPG holding; compressed air | AF8: Electricity + fuel for holding/ladle preheat | AG8: Ladle preheat control, insulation, scheduling
B9: =IF($B$5="","",IFERROR("Levers: "&VLOOKUP($B$5,$AA$4:$AG$108,7,FALSE),"")) -> Levers: Yield optimisation, scrap segregation for recycling | D9: =IF($D$5="","",IFERROR("Levers: "&VLOOKUP($D$5,$AA$4:$AG$108,7,FALSE),"")) -> Levers: Recuperative burners, NG conversion, furnace pressure control, hot charging | F9: =IF($F$5="","",IFERROR("Levers: "&VLOOKUP($F$5,$AA$4:$AG$108,7,FALSE),"")) -> Levers: Servo presses, flash reduction (near-net forging), die-life management | H9: =IF($H$5="","",IFERROR("Levers: "&VLOOKUP($H$5,$AA$4:$AG$108,7,FALSE),"")) -> Levers: Flashless/precision forging to eliminate step | J9: =IF($J$5="","",IFERROR("Levers: "&VLOOKUP($J$5,$AA$4:$AG$108,7,FALSE),"")) -> Levers: Continuous furnace loading optimisation, electric conversion, quench-oil life extension | AA9: FC-06 - Sand casting (green sand line) | AB9: FC-06 | AC9: S2 | AD9: EF-E1 | AE9: Electricity (sand plant, blowers); bentonite, coal dust, new sand | AF9: Electricity; minor process organics (LOI burn-off) | AG9: Sand-to-metal ratio optimisation, sand reclamation, VFDs on blowers
J10: ↓ continues at Step 6 | AA10: FC-07 - Investment casting (lost wax) | AB10: FC-07 | AC10: S1, S2 | AD10: EF-F4, EF-F5, EF-E1 | AE10: Electricity; LPG/NG for dewax & shell firing; wax, zircon/silica slurry | AF10: Fuel for burnout & sintering ovens; electricity | AG10: Oven insulation & scheduling, shell recycling
B11: STEP 6 | D11: STEP 7 | F11: STEP 8 | H11: STEP 9 | J11: STEP 10 | AA11: FC-08 - Core making (cold box / shell) | AB11: FC-08 | AC11: S1, S2 | AD11: EF-E1, EF-F4 | AE11: Electricity; phenolic/furan resins, amine catalyst; LPG (shell) | AF11: Electricity; process VOC/amine emissions (non-GHG); LPG | AG11: Inorganic binder systems, core package optimisation
B12: MC-01 - CNC turning | C12: → | D12: MC-04 - Grinding (surface / cylindrical / centreless) | E12: → | F12: ST-03 - Electroplating (Zn, Zn-Ni, hard Cr, Ni) | G12: → | H12: AT-04 - Metrology & inspection (CMM, vision) | I12: → | J12: VC-02 - Inbound & outbound logistics | AA12: FC-09 - Fettling, grinding & shot blasting | AB12: FC-09 | AC12: S2 | AD12: EF-E1 | AE12: Electricity (grinders, shot blast machines, dust collection) | AF12: Purchased electricity | AG12: High-efficiency motors, blast media management, near-net-shape casting
B13: =IF($B$12="","",IFERROR("Scope: "&VLOOKUP($B$12,$AA$4:$AG$108,3,FALSE)&" | EF: "&VLOOKUP($B$12,$AA$4:$AG$108,4,FALSE),"")) -> Scope: S2 | EF: EF-E1 | D13: =IF($D$12="","",IFERROR("Scope: "&VLOOKUP($D$12,$AA$4:$AG$108,3,FALSE)&" | EF: "&VLOOKUP($D$12,$AA$4:$AG$108,4,FALSE),"")) -> Scope: S2 | EF: EF-E1 | F13: =IF($F$12="","",IFERROR("Scope: "&VLOOKUP($F$12,$AA$4:$AG$108,3,FALSE)&" | EF: "&VLOOKUP($F$12,$AA$4:$AG$108,4,FALSE),"")) -> Scope: S2, S3 | EF: EF-E1, EF-S6 | H13: =IF($H$12="","",IFERROR("Scope: "&VLOOKUP($H$12,$AA$4:$AG$108,3,FALSE)&" | EF: "&VLOOKUP($H$12,$AA$4:$AG$108,4,FALSE),"")) -> Scope: S2 | EF: EF-E1 | J13: =IF($J$12="","",IFERROR("Scope: "&VLOOKUP($J$12,$AA$4:$AG$108,3,FALSE)&" | EF: "&VLOOKUP($J$12,$AA$4:$AG$108,4,FALSE),"")) -> Scope: S3 | EF: EF-T1 to EF-T5 | AA13: FC-10 - Sand reclamation (thermal / mechanical) | AB13: FC-10 | AC13: S1, S2 | AD13: EF-F5, EF-F4, EF-E1 | AE13: Electricity; NG/LPG (thermal reclaim) | AF13: Fuel combustion; electricity | AG13: Mechanical-first reclaim, waste-heat recovery, reduces S3 new-sand transport
B14: =IF($B$12="","",IFERROR("Inputs: "&VLOOKUP($B$12,$AA$4:$AG$108,5,FALSE),"")) -> Inputs: Electricity (spindles, hydraulics, coolant pumps); cutting oil/coolant | D14: =IF($D$12="","",IFERROR("Inputs: "&VLOOKUP($D$12,$AA$4:$AG$108,5,FALSE),"")) -> Inputs: Electricity (high specific energy); grinding wheels, coolant | F14: =IF($F$12="","",IFERROR("Inputs: "&VLOOKUP($F$12,$AA$4:$AG$108,5,FALSE),"")) -> Inputs: Electricity (rectifiers, bath heating); anodes & chemistry; water | H14: =IF($H$12="","",IFERROR("Inputs: "&VLOOKUP($H$12,$AA$4:$AG$108,5,FALSE),"")) -> Inputs: Electricity (incl. lab HVAC) | J14: =IF($J$12="","",IFERROR("Inputs: "&VLOOKUP($J$12,$AA$4:$AG$108,5,FALSE),"")) -> Inputs: Transport fuels (third-party) | AA14: FG-01 - Billet shearing / sawing | AB14: FG-01 | AC14: S2, S3 | AD14: EF-E1, EF-S1 | AE14: Electricity; steel bar stock | AF14: Purchased electricity; upstream steel (S3) | AG14: Yield optimisation, scrap segregation for recycling
B15: =IF($B$12="","",IFERROR("Emissions: "&VLOOKUP($B$12,$AA$4:$AG$108,6,FALSE),"")) -> Emissions: Purchased electricity | D15: =IF($D$12="","",IFERROR("Emissions: "&VLOOKUP($D$12,$AA$4:$AG$108,6,FALSE),"")) -> Emissions: Purchased electricity | F15: =IF($F$12="","",IFERROR("Emissions: "&VLOOKUP($F$12,$AA$4:$AG$108,6,FALSE),"")) -> Emissions: Purchased electricity — rectifiers & heating; zinc/nickel anodes (S3) | H15: =IF($H$12="","",IFERROR("Emissions: "&VLOOKUP($H$12,$AA$4:$AG$108,6,FALSE),"")) -> Emissions: Purchased electricity | J15: =IF($J$12="","",IFERROR("Emissions: "&VLOOKUP($J$12,$AA$4:$AG$108,6,FALSE),"")) -> Emissions: Freight combustion — S3 Categories 4 & 9 | AA15: FG-02 - Billet heating — fuel-fired furnace | AB15: FG-02 | AC15: S1 | AD15: EF-F2, EF-F5 | AE15: Furnace oil / natural gas (30–60 litres FO per tonne typical) | AF15: On-site fuel combustion — LARGEST S1 source in forge shops | AG15: Recuperative burners, NG conversion, furnace pressure control, hot charging
B16: =IF($B$12="","",IFERROR("Levers: "&VLOOKUP($B$12,$AA$4:$AG$108,7,FALSE),"")) -> Levers: Idle-time shutdown, high-efficiency spindles, optimised cutting parameters, MQL | D16: =IF($D$12="","",IFERROR("Levers: "&VLOOKUP($D$12,$AA$4:$AG$108,7,FALSE),"")) -> Levers: Dressing optimisation, superabrasive (CBN) wheels, coolant pump VFDs | F16: =IF($F$12="","",IFERROR("Levers: "&VLOOKUP($F$12,$AA$4:$AG$108,7,FALSE),"")) -> Levers: High-efficiency rectifiers (IGBT), bath temperature control, trivalent chemistry, drag-out reduction | H16: =IF($H$12="","",IFERROR("Levers: "&VLOOKUP($H$12,$AA$4:$AG$108,7,FALSE),"")) -> Levers: Lab HVAC scheduling | J16: =IF($J$12="","",IFERROR("Levers: "&VLOOKUP($J$12,$AA$4:$AG$108,7,FALSE),"")) -> Levers: Rail/coastal modal shift, load-factor optimisation, consolidated milk runs, CNG/LNG/EV fleets | AA16: FG-03 - Billet heating — induction | AB16: FG-03 | AC16: S2 | AD16: EF-E1 | AE16: Grid electricity (~350–450 kWh/t) | AF16: Purchased electricity | AG16: Coil matching, RE power, standby-loss control
AA17: FG-04 - Hot / warm forging (press or hammer) | AB17: FG-04 | AC17: S2 | AD17: EF-E1 | AE17: Electricity (press drives, compressors); die lube, graphite | AF17: Purchased electricity | AG17: Servo presses, flash reduction (near-net forging), die-life management
B18: ROUTE SUMMARY | AA18: FG-05 - Cold forging / cold heading | AB18: FG-05 | AC18: S2 | AD18: EF-E1 | AE18: Electricity; steel wire/coil; phosphate-soap lube | AF18: Purchased electricity; pre-treatment chemicals | AG18: High-speed headers, tool coatings, eliminating downstream machining
B19: Steps selected in this route | G19: =IF(B5<>"",1,0)+IF(D5<>"",1,0)+IF(F5<>"",1,0)+IF(H5<>"",1,0)+IF(J5<>"",1,0)+IF(B12<>"",1,0)+IF(D12<>"",1,0)+IF(F12<>"",1,0)+IF(H12<>"",1,0)+IF(J12<>"",1,0) -> 10 | AA19: FG-06 - Ring rolling | AB19: FG-06 | AC19: S1, S2 | AD19: EF-F2, EF-F5, EF-E1 | AE19: Electricity; billet heating fuel | AF19: Fuel (S1) + electricity (S2) | AG19: Near-net rolling, recuperators
B20: Steps with on-site fuel / process emissions (Scope 1) | G20: =IF(B5="",0,IF(ISNUMBER(FIND("S1",IFERROR(VLOOKUP(B5,$AA$4:$AG$108,3,FALSE),""))),1,0))+IF(D5="",0,IF(ISNUMBER(FIND("S1",IFERROR(VLOOKUP(D5,$AA$4:$AG$108,3,FALSE),""))),1,0))+IF(F5="",0,IF(ISNUMBER(FIND("S1",IFERROR(VLOOKUP(F5,$AA$4:$AG$108,3,FALSE),""))),1,0))+IF(H5="",0,IF(ISNUMBER(FIND("S1",IFERROR(VLOOKUP(H5,$AA$4:$AG$108,3,FALSE),""))),1,0))+IF(J5="",0,IF(ISNUMBER(FIND("S1",IFERROR(VLOOKUP(J5,$AA$4:$AG$108,3,FALSE),""))),1,0))+IF(B12="",0,IF(ISNUMBER(FIND("S1",IFERROR(VLOOKUP(B12,$AA$4:$AG$108,3,FALSE),""))),1,0))+IF(D12="",0,IF(ISNUMBER(FIND("S1",IFERROR(VLOOKUP(D12,$AA$4:$AG$108,3,FALSE),""))),1,0))+IF(F12="",0,IF(ISNUMBER(FIND("S1",IFERROR(VLOOKUP(F12,$AA$4:$AG$108,3,FALSE),""))),1,0))+IF(H12="",0,IF(ISNUMBER(FIND("S1",IFERROR(VLOOKUP(H12,$AA$4:$AG$108,3,FALSE),""))),1,0))+IF(J12="",0,IF(ISNUMBER(FIND("S1",IFERROR(VLOOKUP(J12,$AA$4:$AG$108,3,FALSE),""))),1,0)) -> 2 | AA20: FG-07 - Trimming, piercing & coining | AB20: FG-07 | AC20: S2 | AD20: EF-E1 | AE20: Electricity | AF20: Purchased electricity | AG20: Flashless/precision forging to eliminate step
B21: Steps drawing purchased electricity (Scope 2) | G21: =IF(B5="",0,IF(ISNUMBER(FIND("S2",IFERROR(VLOOKUP(B5,$AA$4:$AG$108,3,FALSE),""))),1,0))+IF(D5="",0,IF(ISNUMBER(FIND("S2",IFERROR(VLOOKUP(D5,$AA$4:$AG$108,3,FALSE),""))),1,0))+IF(F5="",0,IF(ISNUMBER(FIND("S2",IFERROR(VLOOKUP(F5,$AA$4:$AG$108,3,FALSE),""))),1,0))+IF(H5="",0,IF(ISNUMBER(FIND("S2",IFERROR(VLOOKUP(H5,$AA$4:$AG$108,3,FALSE),""))),1,0))+IF(J5="",0,IF(ISNUMBER(FIND("S2",IFERROR(VLOOKUP(J5,$AA$4:$AG$108,3,FALSE),""))),1,0))+IF(B12="",0,IF(ISNUMBER(FIND("S2",IFERROR(VLOOKUP(B12,$AA$4:$AG$108,3,FALSE),""))),1,0))+IF(D12="",0,IF(ISNUMBER(FIND("S2",IFERROR(VLOOKUP(D12,$AA$4:$AG$108,3,FALSE),""))),1,0))+IF(F12="",0,IF(ISNUMBER(FIND("S2",IFERROR(VLOOKUP(F12,$AA$4:$AG$108,3,FALSE),""))),1,0))+IF(H12="",0,IF(ISNUMBER(FIND("S2",IFERROR(VLOOKUP(H12,$AA$4:$AG$108,3,FALSE),""))),1,0))+IF(J12="",0,IF(ISNUMBER(FIND("S2",IFERROR(VLOOKUP(J12,$AA$4:$AG$108,3,FALSE),""))),1,0)) -> 8 | AA21: MC-01 - CNC turning | AB21: MC-01 | AC21: S2 | AD21: EF-E1 | AE21: Electricity (spindles, hydraulics, coolant pumps); cutting oil/coolant | AF21: Purchased electricity | AG21: Idle-time shutdown, high-efficiency spindles, optimised cutting parameters, MQL
B22: Steps with material / value-chain relevance (Scope 3) | G22: =IF(B5="",0,IF(ISNUMBER(FIND("S3",IFERROR(VLOOKUP(B5,$AA$4:$AG$108,3,FALSE),""))),1,0))+IF(D5="",0,IF(ISNUMBER(FIND("S3",IFERROR(VLOOKUP(D5,$AA$4:$AG$108,3,FALSE),""))),1,0))+IF(F5="",0,IF(ISNUMBER(FIND("S3",IFERROR(VLOOKUP(F5,$AA$4:$AG$108,3,FALSE),""))),1,0))+IF(H5="",0,IF(ISNUMBER(FIND("S3",IFERROR(VLOOKUP(H5,$AA$4:$AG$108,3,FALSE),""))),1,0))+IF(J5="",0,IF(ISNUMBER(FIND("S3",IFERROR(VLOOKUP(J5,$AA$4:$AG$108,3,FALSE),""))),1,0))+IF(B12="",0,IF(ISNUMBER(FIND("S3",IFERROR(VLOOKUP(B12,$AA$4:$AG$108,3,FALSE),""))),1,0))+IF(D12="",0,IF(ISNUMBER(FIND("S3",IFERROR(VLOOKUP(D12,$AA$4:$AG$108,3,FALSE),""))),1,0))+IF(F12="",0,IF(ISNUMBER(FIND("S3",IFERROR(VLOOKUP(F12,$AA$4:$AG$108,3,FALSE),""))),1,0))+IF(H12="",0,IF(ISNUMBER(FIND("S3",IFERROR(VLOOKUP(H12,$AA$4:$AG$108,3,FALSE),""))),1,0))+IF(J12="",0,IF(ISNUMBER(FIND("S3",IFERROR(VLOOKUP(J12,$AA$4:$AG$108,3,FALSE),""))),1,0)) -> 3 | AA22: MC-02 - Milling / machining centres (VMC/HMC) | AB22: MC-02 | AC22: S2 | AD22: EF-E1 | AE22: Electricity; tooling, coolant | AF22: Purchased electricity | AG22: Fixture/multi-op consolidation, machine monitoring (GF360 IoT), RE power
AA23: MC-03 - Drilling, tapping & boring | AB23: MC-03 | AC23: S2 | AD23: EF-E1 | AE23: Electricity | AF23: Purchased electricity | AG23: Combined tooling, process consolidation
B24: Tip: pair this sheet with 'Emission Factors (India)' — the EF codes shown under each step point to the default factors to apply — and with the pre-drawn routes on 'Process Flow Diagrams'. To model a plant with more than 10 steps, split the route into two builder passes or duplicate this sheet (right-click the tab > Move or Copy > Create a copy). | AA24: MC-04 - Grinding (surface / cylindrical / centreless) | AB24: MC-04 | AC24: S2 | AD24: EF-E1 | AE24: Electricity (high specific energy); grinding wheels, coolant | AF24: Purchased electricity | AG24: Dressing optimisation, superabrasive (CBN) wheels, coolant pump VFDs
AA25: MC-05 - Honing / lapping / superfinishing | AB25: MC-05 | AC25: S2 | AD25: EF-E1 | AE25: Electricity; honing oil, abrasives | AF25: Purchased electricity | AG25: Process parameter optimisation
AA26: MC-06 - Gear cutting (hobbing / shaping / shaving / grinding) | AB26: MC-06 | AC26: S2 | AD26: EF-E1 | AE26: Electricity; hobs & cutters, cutting oil | AF26: Purchased electricity | AG26: Dry/hard hobbing, skiving, tool coatings
AA27: MC-07 - Broaching | AB27: MC-07 | AC27: S2 | AD27: EF-E1 | AE27: Electricity | AF27: Purchased electricity | AG27: Tooling life management
AA28: MC-08 - EDM / wire-cut (tool room) | AB28: MC-08 | AC28: S2 | AD28: EF-E1 | AE28: Electricity; dielectric fluid, brass wire | AF28: Purchased electricity | AG28: Generator efficiency modes
AA29: MC-09 - Coolant, chip & oil-mist management | AB29: MC-09 | AC29: S2, S3 | AD29: EF-E1 | AE29: Electricity; coolants & additives (S3); waste oil disposal (S3) | AF29: Purchased electricity; waste treatment (S3) | AG29: Centralised coolant systems, chip briquetting (better scrap value & lower transport)
AA30: SM-01 - Coil slitting / decoiling / blanking | AB30: SM-01 | AC30: S2, S3 | AD30: EF-E1, EF-S1, EF-S3 | AE30: Electricity; steel/Al coil (S3, CBAM-relevant input) | AF30: Purchased electricity; upstream metal (S3) | AG30: Nesting/yield optimisation (directly cuts S3), scrap segregation
AA31: SM-02 - Press stamping / deep drawing | AB31: SM-02 | AC31: S2 | AD31: EF-E1 | AE31: Electricity (press drives, compressed air); drawing lube | AF31: Purchased electricity | AG31: Servo press retrofits, die cushion energy recovery, compressed-air leak control
AA32: SM-03 - Fine blanking | AB32: SM-03 | AC32: S2 | AD32: EF-E1 | AE32: Electricity | AF32: Purchased electricity | AG32: Tool life & material utilisation
AA33: SM-04 - Roll forming / ERW tube mills | AB33: SM-04 | AC33: S2 | AD33: EF-E1 | AE33: Electricity (mill drives, HF welder) | AF33: Purchased electricity | AG33: HF welder efficiency, line speed optimisation
AA34: SM-05 - Tube bending & end forming | AB34: SM-05 | AC34: S2 | AD34: EF-E1 | AE34: Electricity; mandrel lube | AF34: Purchased electricity | AG34: CNC benders, right-first-time quality
AA35: SM-06 - Laser / plasma / waterjet cutting | AB35: SM-06 | AC35: S2 | AD35: EF-E1 | AE35: Electricity; assist gases (N2, O2); plasma gas | AF35: Purchased electricity; minor process gases | AG35: Fiber laser upgrades (vs CO2 laser), nesting software
AA36: SM-07 - CNC press brake bending | AB36: SM-07 | AC36: S2 | AD36: EF-E1 | AE36: Electricity | AF36: Purchased electricity | AG36: Electric (servo) press brakes
... AA108: VC-06 - Use phase & end-of-life of sold products | AB108: VC-06 | AC108: S3 | AD108: — | AE108: In-vehicle energy over component life | AF108: S3 Categories 11 & 12 | AG108: Lightweighting, low-friction design, design-for-recycling — quantify in GF360 LCA module

Sheet Cost of Inaction
A1: COST OF INACTION — BASELINE WITHOUT GF360
B3: Year 1 | C3: Year 2 | D3: Year 3 | E3: Year 4 | F3: Year 5 | G3: 5-Yr Total
A4: Baseline Revenue & Emissions (Intermediate Calculation)
A5: Total Annual Turnover (Rs Cr) | B5: ='Client Inputs'!$B$6 -> 250 | C5: =B5*(1+'Client Inputs'!$B$7) -> 270 | D5: =C5*(1+'Client Inputs'!$B$7) -> 291.6 | E5: =D5*(1+'Client Inputs'!$B$7) -> 314.928 | F5: =E5*(1+'Client Inputs'!$B$7) -> 340.12224 | G5: (stock — not summed)
A6: EU Export Revenue (Rs Cr) | B6: =B5*'Client Inputs'!$B$10 -> 45 | C6: =C5*'Client Inputs'!$B$10 -> 48.6 | D6: =D5*'Client Inputs'!$B$10 -> 52.488 | E6: =E5*'Client Inputs'!$B$10 -> 56.68704 | F6: =F5*'Client Inputs'!$B$10 -> 61.222003 | G6: (stock — not summed)
A7: Embedded Emissions Subject to CBAM (tCO2e) | B7: =B6*'Client Inputs'!$B$13 -> 2025 | C7: =C6*'Client Inputs'!$B$13 -> 2187 | D7: =D6*'Client Inputs'!$B$13 -> 2361.96 | E7: =E6*'Client Inputs'!$B$13 -> 2550.9168 | F7: =F6*'Client Inputs'!$B$13 -> 2754.9901 | G7: (stock — not summed)
A9: Hard Costs of Inaction (Without GF360)
A10: CBAM Liability at Default Values (Rs Lakh) | B10: =B7*'Client Inputs'!$B$28*'Client Inputs'!$B$29*(1+'Client Inputs'!$B$30)/100000 -> 212.57438 | C10: =C7*'Client Inputs'!$B$28*'Client Inputs'!$B$29*(1+'Client Inputs'!$B$30)/100000 -> 229.58032 | D10: =D7*'Client Inputs'!$B$28*'Client Inputs'!$B$29*(1+'Client Inputs'!$B$30)/100000 -> 247.94675 | E10: =E7*'Client Inputs'!$B$28*'Client Inputs'!$B$29*(1+'Client Inputs'!$B$30)/100000 -> 267.78249 | F10: =F7*'Client Inputs'!$B$28*'Client Inputs'!$B$29*(1+'Client Inputs'!$B$30)/100000 -> 289.20509 | G10: =SUM(B10:F10) -> 1247.089
A11: Annual Consultant / Big-4 Assessment Fee (Rs Lakh) | B11: ='Client Inputs'!$B$34 -> 35 | C11: ='Client Inputs'!$B$34 -> 35 | D11: ='Client Inputs'!$B$34 -> 35 | E11: ='Client Inputs'!$B$34 -> 35 | F11: ='Client Inputs'!$B$34 -> 35 | G11: =SUM(B11:F11) -> 175
A12: Internal Staff Time Cost — Manual Data Collection (Rs Lakh) | B12: ='Client Inputs'!$B$15*'Client Inputs'!$B$14/100000 -> 2.7 | C12: ='Client Inputs'!$B$15*'Client Inputs'!$B$14/100000 -> 2.7 | D12: ='Client Inputs'!$B$15*'Client Inputs'!$B$14/100000 -> 2.7 | E12: ='Client Inputs'!$B$15*'Client Inputs'!$B$14/100000 -> 2.7 | F12: ='Client Inputs'!$B$15*'Client Inputs'!$B$14/100000 -> 2.7 | G12: =SUM(B12:F12) -> 13.5
A13: Subtotal — Hard Cost of Inaction (Rs Lakh) | B13: =SUM(B10:B12) -> 250.27437 | C13: =SUM(C10:C12) -> 267.28033 | D13: =SUM(D10:D12) -> 285.64675 | E13: =SUM(E10:E12) -> 305.48249 | F13: =SUM(F10:F12) -> 326.90509 | G13: =SUM(B13:F13) -> 1435.589
A15: Risk-Adjusted Exposure (Illustrative — Shown Separately)
A16: OEM / Tier-1-Linked Revenue Requiring ESG Data (Rs Cr) | B16: =B5*'Client Inputs'!$B$11 -> 100 | C16: =C5*'Client Inputs'!$B$11 -> 108 | D16: =D5*'Client Inputs'!$B$11 -> 116.64 | E16: =E5*'Client Inputs'!$B$11 -> 125.9712 | F16: =F5*'Client Inputs'!$B$11 -> 136.0489 | G16: (stock — not summed)
A17: Total Revenue Base at Compliance Risk (Rs Cr) | B17: =B6+B16 -> 145 | C17: =C6+C16 -> 156.6 | D17: =D6+D16 -> 169.128 | E17: =E6+E16 -> 182.65824 | F17: =F6+F16 -> 197.2709 | G17: (stock — not summed)
A18: Probability-Weighted Margin-at-Risk (Rs Lakh) | B18: =B17*100*'Client Inputs'!$B$38*'Client Inputs'!$B$35 -> 261 | C18: =C17*100*'Client Inputs'!$B$38*'Client Inputs'!$B$35 -> 281.88 | D18: =D17*100*'Client Inputs'!$B$38*'Client Inputs'!$B$35 -> 304.4304 | E18: =E17*100*'Client Inputs'!$B$38*'Client Inputs'!$B$35 -> 328.78483 | F18: =F17*100*'Client Inputs'!$B$38*'Client Inputs'!$B$35 -> 355.08762 | G18: =SUM(B18:F18) -> 1531.1829
A20: Total Cost of Inaction Incl. Risk Exposure (Rs Lakh) | B20: =B13+B18 -> 511.27437 | C20: =C13+C18 -> 549.16032 | D20: =D13+D18 -> 590.07715 | E20: =E13+E18 -> 634.26732 | F20: =F13+F18 -> 681.99271 | G20: =SUM(B20:F20) -> 2966.7719

Sheet GF360 Investment
A1: GF360 INVESTMENT (COST) — 5-YEAR VIEW
B3: Year 1 | C3: Year 2 | D3: Year 3 | E3: Year 4 | F3: Year 5 | G3: 5-Yr Total
A4: Annual Subscription Fee (Rs Lakh) | B4: ='Client Inputs'!$B$19 -> 8 | C4: =B4*(1+'Client Inputs'!$B$23) -> 8.4 | D4: =C4*(1+'Client Inputs'!$B$23) -> 8.82 | E4: =D4*(1+'Client Inputs'!$B$23) -> 9.261 | F4: =E4*(1+'Client Inputs'!$B$23) -> 9.72405 | G4: =SUM(B4:F4) -> 44.20505
A5: One-time Implementation / Onboarding Fee (Rs Lakh) | B5: ='Client Inputs'!$B$20 -> 2.5 | C5: 0 | D5: 0 | E5: 0 | F5: 0 | G5: =SUM(B5:F5) -> 2.5
A6: Advisory / Verification Support Bundle (Rs Lakh) | B6: ='Client Inputs'!$B$21 -> 3 | C6: =B6*(1+'Client Inputs'!$B$23) -> 3.15 | D6: =C6*(1+'Client Inputs'!$B$23) -> 3.3075 | E6: =D6*(1+'Client Inputs'!$B$23) -> 3.472875 | F6: =E6*(1+'Client Inputs'!$B$23) -> 3.6465188 | G6: =SUM(B6:F6) -> 16.576894
A7: Total Annual Investment (Rs Lakh) | B7: =SUM(B4:B6) -> 13.5 | C7: =SUM(C4:C6) -> 11.55 | D7: =SUM(D4:D6) -> 12.1275 | E7: =SUM(E4:E6) -> 12.733875 | F7: =SUM(F4:F6) -> 13.370569 | G7: =SUM(B7:F7) -> 63.281944
A8: Cumulative Investment (Rs Lakh) | B8: =B7 -> 13.5 | C8: =B8+C7 -> 25.05 | D8: =C8+D7 -> 37.1775 | E8: =D8+E7 -> 49.911375 | F8: =E8+F7 -> 63.281944 | G8: =F8 -> 63.281944

Sheet GF360 Benefits
A1: GF360 BENEFITS — 5-YEAR VIEW
B3: Year 1 | C3: Year 2 | D3: Year 3 | E3: Year 4 | F3: Year 5 | G3: 5-Yr Total
A4: Direct Cost Avoidance
A5: CBAM Cost Avoidance — Premium Portion (Rs Lakh) | B5: ='Cost of Inaction'!B7*'Client Inputs'!$B$28*'Client Inputs'!$B$29*'Client Inputs'!$B$30/100000 -> 49.055625 | C5: ='Cost of Inaction'!C7*'Client Inputs'!$B$28*'Client Inputs'!$B$29*'Client Inputs'!$B$30/100000 -> 52.980075 | D5: ='Cost of Inaction'!D7*'Client Inputs'!$B$28*'Client Inputs'!$B$29*'Client Inputs'!$B$30/100000 -> 57.218481 | E5: ='Cost of Inaction'!E7*'Client Inputs'!$B$28*'Client Inputs'!$B$29*'Client Inputs'!$B$30/100000 -> 61.795959 | F5: ='Cost of Inaction'!F7*'Client Inputs'!$B$28*'Client Inputs'!$B$29*'Client Inputs'!$B$30/100000 -> 66.739636 | G5: =SUM(B5:F5) -> 287.78978
A6: Avoided Consultant / Big-4 Assessment Fee (Rs Lakh) | B6: ='Cost of Inaction'!B11 -> 35 | C6: ='Cost of Inaction'!C11 -> 35 | D6: ='Cost of Inaction'!D11 -> 35 | E6: ='Cost of Inaction'!E11 -> 35 | F6: ='Cost of Inaction'!F11 -> 35 | G6: =SUM(B6:F6) -> 175
A7: Internal Staff Time Savings via Automation (Rs Lakh) | B7: ='Cost of Inaction'!B12*'Client Inputs'!$B$24 -> 1.89 | C7: ='Cost of Inaction'!C12*'Client Inputs'!$B$24 -> 1.89 | D7: ='Cost of Inaction'!D12*'Client Inputs'!$B$24 -> 1.89 | E7: ='Cost of Inaction'!E12*'Client Inputs'!$B$24 -> 1.89 | F7: ='Cost of Inaction'!F12*'Client Inputs'!$B$24 -> 1.89 | G7: =SUM(B7:F7) -> 9.45
A9: Operational Efficiency Savings
A10: Energy Efficiency Savings from Decarbonisation Roadmap (Rs Lakh) | B10: ='Client Inputs'!$B$9*'Client Inputs'!$B$31 -> 13.5 | C10: ='Client Inputs'!$B$9*'Client Inputs'!$B$32 -> 36 | D10: ='Client Inputs'!$B$9*'Client Inputs'!$B$33 -> 54 | E10: ='Client Inputs'!$B$9*'Client Inputs'!$B$33 -> 54 | F10: ='Client Inputs'!$B$9*'Client Inputs'!$B$33 -> 54 | G10: =SUM(B10:F10) -> 211.5
A12: Subtotal — Hard Benefits (Rs Lakh) | B12: =B5+B6+B7+B10 -> 99.445625 | C12: =C5+C6+C7+C10 -> 125.87007 | D12: =D5+D6+D7+D10 -> 148.10848 | E12: =E5+E6+E7+E10 -> 152.68596 | F12: =F5+F6+F7+F10 -> 157.62964 | G12: =SUM(B12:F12) -> 683.73978
A14: Risk Mitigation Value (Illustrative — Shown Separately)
A15: Risk Mitigation Value (Rs Lakh) | B15: ='Cost of Inaction'!B18*'Client Inputs'!$B$36 -> 208.8 | C15: ='Cost of Inaction'!C18*'Client Inputs'!$B$36 -> 225.504 | D15: ='Cost of Inaction'!D18*'Client Inputs'!$B$36 -> 243.54432 | E15: ='Cost of Inaction'!E18*'Client Inputs'!$B$36 -> 263.02787 | F15: ='Cost of Inaction'!F18*'Client Inputs'!$B$36 -> 284.07009 | G15: =SUM(B15:F15) -> 1224.9463
A17: Total Benefits Incl. Risk Mitigation (Rs Lakh) | B17: =B12+B15 -> 308.24563 | C17: =C12+C15 -> 351.37407 | D17: =D12+D15 -> 391.6528 | E17: =E12+E15 -> 415.71383 | F17: =F12+F15 -> 441.69973 | G17: =SUM(B17:F17) -> 1908.6861

Sheet ROI Summary
A1: ROI SUMMARY DASHBOARD
B3: Year 1 | C3: Year 2 | D3: Year 3 | E3: Year 4 | F3: Year 5 | G3: 5-Yr Total
A4: Total Investment (Rs Lakh) | B4: ='GF360 Investment'!B7 -> 13.5 | C4: ='GF360 Investment'!C7 -> 11.55 | D4: ='GF360 Investment'!D7 -> 12.1275 | E4: ='GF360 Investment'!E7 -> 12.733875 | F4: ='GF360 Investment'!F7 -> 13.370569 | G4: ='GF360 Investment'!G7 -> 63.281944
A5: Total Benefits — Hard (Rs Lakh) | B5: ='GF360 Benefits'!B12 -> 99.445625 | C5: ='GF360 Benefits'!C12 -> 125.87007 | D5: ='GF360 Benefits'!D12 -> 148.10848 | E5: ='GF360 Benefits'!E12 -> 152.68596 | F5: ='GF360 Benefits'!F12 -> 157.62964 | G5: ='GF360 Benefits'!G12 -> 683.73978
A6: Net Benefit — Hard (Rs Lakh) | B6: =B5-B4 -> 85.945625 | C6: =C5-C4 -> 114.32008 | D6: =D5-D4 -> 135.98098 | E6: =E5-E4 -> 139.95208 | F6: =F5-F4 -> 144.25907 | G6: =SUM(B6:F6) -> 620.45783
A7: Cumulative Net Benefit — Hard (Rs Lakh) | B7: =B6 -> 85.945625 | C7: =B7+C6 -> 200.2657 | D7: =C7+D6 -> 336.24668 | E7: =D7+E6 -> 476.19877 | F7: =E7+F6 -> 620.45783 | G7: =F7 -> 620.45783
A9: Total Benefits Incl. Risk Mitigation (Rs Lakh) | B9: ='GF360 Benefits'!B17 -> 308.24563 | C9: ='GF360 Benefits'!C17 -> 351.37407 | D9: ='GF360 Benefits'!D17 -> 391.6528 | E9: ='GF360 Benefits'!E17 -> 415.71383 | F9: ='GF360 Benefits'!F17 -> 441.69973 | G9: ='GF360 Benefits'!G17 -> 1908.6861
A10: Net Benefit Incl. Risk Mitigation (Rs Lakh) | B10: =B9-B4 -> 294.74563 | C10: =C9-C4 -> 339.82407 | D10: =D9-D4 -> 379.5253 | E10: =E9-E4 -> 402.97995 | F10: =F9-F4 -> 428.32916 | G10: =SUM(B10:F10) -> 1845.4041
A11: Cumulative Net Benefit Incl. Risk (Rs Lakh) | B11: =B10 -> 294.74563 | C11: =B11+C10 -> 634.5697 | D11: =C11+D10 -> 1014.095 | E11: =D11+E10 -> 1417.075 | F11: =E11+F10 -> 1845.4041 | G11: =F11 -> 1845.4041
A13: KEY METRICS SUMMARY
A14: Metric | B14: Hard Benefits Only | C14: Incl. Risk Mitigation
A15: 5-Year Net Benefit (Rs Lakh) | B15: =G6 -> 620.45783 | C15: =G10 -> 1845.4041
A16: 5-Year ROI % | B16: =G6/G4 -> 9.8046583 | C16: =G10/G4 -> 29.161622
A17: Payback Period (Months, approx.) | B17: =IFERROR(IF('GF360 Investment'!$B$5<=0,0,IF(B7>=0,'GF360 Investment'!$B$5*12/(B6+'GF360 Investment'!$B$5),IF(C7>=0,(0-B7)/C6*12+12,IF(D7>=0,(0-C7)/D6*12+24,IF(E7>=0,(0-D7)/E6*12+36,IF(F7>=0,(0-E7)/F6*12+48,"> 5 years")))))),"> 5 years") -> 0.33919145 | C17: =IFERROR(IF('GF360 Investment'!$B$5<=0,0,IF(B11>=0,'GF360 Investment'!$B$5*12/(B10+'GF360 Investment'!$B$5),IF(C11>=0,(0-B11)/C10*12+12,IF(D11>=0,(0-C11)/D10*12+24,IF(E11>=0,(0-D11)/E10*12+36,IF(F11>=0,(0-E11)/F10*12+48,"> 5 years")))))),"> 5 years") -> 0.10092663
A18: NPV at Discount Rate (Rs Lakh) | B18: =NPV('Client Inputs'!$B$37,B6:F6) -> 459.939 | C18: =NPV('Client Inputs'!$B$37,B10:F10) -> 1375.1393
A19: IRR (%) | B19: =IFERROR(IRR(B6:F6),"N/A – positive from Yr 1") -> N/A – positive from Yr 1 | C19: =IFERROR(IRR(B10:F10),"N/A – positive from Yr 1") -> N/A – positive from Yr 1
A42: 5-Yr Benefit Composition (Helper — Hard Benefits)
A43: CBAM Cost Avoidance | B43: ='GF360 Benefits'!G5 -> 287.78978
A44: Avoided Consultant / Big-4 Fee | B44: ='GF360 Benefits'!G6 -> 175
A45: Staff Time Savings | B45: ='GF360 Benefits'!G7 -> 9.45
A46: Energy Efficiency Savings | B46: ='GF360 Benefits'!G10 -> 211.5

Sheet Sensitivity
A1: SENSITIVITY ANALYSIS
A3: A. Scenario Table — Benefit Realisation Multiplier
B5: Benefit Multiplier | C5: 5-Yr Benefits (Rs Lakh) | D5: 5-Yr Investment (Rs Lakh) | E5: 5-Yr Net Benefit (Rs Lakh) | F5: 5-Yr ROI % | G5: Approx. Payback (Months)
A6: Conservative | B6: 0.7 | C6: ='ROI Summary'!G5*B6 -> 478.61784 | D6: ='ROI Summary'!G4 -> 63.281944 | E6: =C6-D6 -> 415.3359 | F6: =E6/D6 -> 6.5632608 | G6: =D6/(C6/5)*12 -> 7.9330862
A7: Base Case | B7: 1 | C7: ='ROI Summary'!G5*B7 -> 683.73978 | D7: ='ROI Summary'!G4 -> 63.281944 | E7: =C7-D7 -> 620.45783 | F7: =E7/D7 -> 9.8046583 | G7: =D7/(C7/5)*12 -> 5.5531604
A8: Aggressive | B8: 1.3 | C8: ='ROI Summary'!G5*B8 -> 888.86171 | D8: ='ROI Summary'!G4 -> 63.281944 | E8: =C8-D8 -> 825.57977 | F8: =E8/D8 -> 13.046056 | G8: =D8/(C8/5)*12 -> 4.2716618
A10: Payback shown here is a straight-line approximation (5-yr investment ÷ average annual benefit); see 'ROI Summary' for the year-by-year payback calculation.
A12: B. 5-Year ROI % Sensitivity Grid — EU Export Share vs. Energy Savings (Static Approximation)
A14: EU Export % ↓ / Energy Savings % → | B14: 0.08 | C14: 0.1 | D14: 0.12 | E14: 0.15 | F14: 0.18
A15: 0.1 | B15: =(('Client Inputs'!$B$6*$A15*'Client Inputs'!$B$13*'Client Inputs'!$B$28*'Client Inputs'!$B$29*'Client Inputs'!$B$30/100000+'Client Inputs'!$B$34+'Client Inputs'!$B$15*'Client Inputs'!$B$14/100000*'Client Inputs'!$B$24+'Client Inputs'!$B$9*B$14)*5-'ROI Summary'!$G$4)/'ROI Summary'!$G$4 -> 6.9124565 | C15: =(('Client Inputs'!$B$6*$A15*'Client Inputs'!$B$13*'Client Inputs'!$B$28*'Client Inputs'!$B$29*'Client Inputs'!$B$30/100000+'Client Inputs'!$B$34+'Client Inputs'!$B$15*'Client Inputs'!$B$14/100000*'Client Inputs'!$B$24+'Client Inputs'!$B$9*C$14)*5-'ROI Summary'!$G$4)/'ROI Summary'!$G$4 -> 7.6235598 | D15: =(('Client Inputs'!$B$6*$A15*'Client Inputs'!$B$13*'Client Inputs'!$B$28*'Client Inputs'!$B$29*'Client Inputs'!$B$30/100000+'Client Inputs'!$B$34+'Client Inputs'!$B$15*'Client Inputs'!$B$14/100000*'Client Inputs'!$B$24+'Client Inputs'!$B$9*D$14)*5-'ROI Summary'!$G$4)/'ROI Summary'!$G$4 -> 8.3346631 | E15: =(('Client Inputs'!$B$6*$A15*'Client Inputs'!$B$13*'Client Inputs'!$B$28*'Client Inputs'!$B$29*'Client Inputs'!$B$30/100000+'Client Inputs'!$B$34+'Client Inputs'!$B$15*'Client Inputs'!$B$14/100000*'Client Inputs'!$B$24+'Client Inputs'!$B$9*E$14)*5-'ROI Summary'!$G$4)/'ROI Summary'!$G$4 -> 9.4013181 | F15: =(('Client Inputs'!$B$6*$A15*'Client Inputs'!$B$13*'Client Inputs'!$B$28*'Client Inputs'!$B$29*'Client Inputs'!$B$30/100000+'Client Inputs'!$B$34+'Client Inputs'!$B$15*'Client Inputs'!$B$14/100000*'Client Inputs'!$B$24+'Client Inputs'!$B$9*F$14)*5-'ROI Summary'!$G$4)/'ROI Summary'!$G$4 -> 10.467973
A16: 0.15 | B16: =(('Client Inputs'!$B$6*$A16*'Client Inputs'!$B$13*'Client Inputs'!$B$28*'Client Inputs'!$B$29*'Client Inputs'!$B$30/100000+'Client Inputs'!$B$34+'Client Inputs'!$B$15*'Client Inputs'!$B$14/100000*'Client Inputs'!$B$24+'Client Inputs'!$B$9*B$14)*5-'ROI Summary'!$G$4)/'ROI Summary'!$G$4 -> 7.9891113 | C16: =(('Client Inputs'!$B$6*$A16*'Client Inputs'!$B$13*'Client Inputs'!$B$28*'Client Inputs'!$B$29*'Client Inputs'!$B$30/100000+'Client Inputs'!$B$34+'Client Inputs'!$B$15*'Client Inputs'!$B$14/100000*'Client Inputs'!$B$24+'Client Inputs'!$B$9*C$14)*5-'ROI Summary'!$G$4)/'ROI Summary'!$G$4 -> 8.7002146 | D16: =(('Client Inputs'!$B$6*$A16*'Client Inputs'!$B$13*'Client Inputs'!$B$28*'Client Inputs'!$B$29*'Client Inputs'!$B$30/100000+'Client Inputs'!$B$34+'Client Inputs'!$B$15*'Client Inputs'!$B$14/100000*'Client Inputs'!$B$24+'Client Inputs'!$B$9*D$14)*5-'ROI Summary'!$G$4)/'ROI Summary'!$G$4 -> 9.411318 | E16: =(('Client Inputs'!$B$6*$A16*'Client Inputs'!$B$13*'Client Inputs'!$B$28*'Client Inputs'!$B$29*'Client Inputs'!$B$30/100000+'Client Inputs'!$B$34+'Client Inputs'!$B$15*'Client Inputs'!$B$14/100000*'Client Inputs'!$B$24+'Client Inputs'!$B$9*E$14)*5-'ROI Summary'!$G$4)/'ROI Summary'!$G$4 -> 10.477973 | F16: =(('Client Inputs'!$B$6*$A16*'Client Inputs'!$B$13*'Client Inputs'!$B$28*'Client Inputs'!$B$29*'Client Inputs'!$B$30/100000+'Client Inputs'!$B$34+'Client Inputs'!$B$15*'Client Inputs'!$B$14/100000*'Client Inputs'!$B$24+'Client Inputs'!$B$9*F$14)*5-'ROI Summary'!$G$4)/'ROI Summary'!$G$4 -> 11.544628
A17: 0.18 | B17: =(('Client Inputs'!$B$6*$A17*'Client Inputs'!$B$13*'Client Inputs'!$B$28*'Client Inputs'!$B$29*'Client Inputs'!$B$30/100000+'Client Inputs'!$B$34+'Client Inputs'!$B$15*'Client Inputs'!$B$14/100000*'Client Inputs'!$B$24+'Client Inputs'!$B$9*B$14)*5-'ROI Summary'!$G$4)/'ROI Summary'!$G$4 -> 8.6351042 | C17: =(('Client Inputs'!$B$6*$A17*'Client Inputs'!$B$13*'Client Inputs'!$B$28*'Client Inputs'!$B$29*'Client Inputs'!$B$30/100000+'Client Inputs'!$B$34+'Client Inputs'!$B$15*'Client Inputs'!$B$14/100000*'Client Inputs'!$B$24+'Client Inputs'!$B$9*C$14)*5-'ROI Summary'!$G$4)/'ROI Summary'!$G$4 -> 9.3462076 | D17: =(('Client Inputs'!$B$6*$A17*'Client Inputs'!$B$13*'Client Inputs'!$B$28*'Client Inputs'!$B$29*'Client Inputs'!$B$30/100000+'Client Inputs'!$B$34+'Client Inputs'!$B$15*'Client Inputs'!$B$14/100000*'Client Inputs'!$B$24+'Client Inputs'!$B$9*D$14)*5-'ROI Summary'!$G$4)/'ROI Summary'!$G$4 -> 10.057311 | E17: =(('Client Inputs'!$B$6*$A17*'Client Inputs'!$B$13*'Client Inputs'!$B$28*'Client Inputs'!$B$29*'Client Inputs'!$B$30/100000+'Client Inputs'!$B$34+'Client Inputs'!$B$15*'Client Inputs'!$B$14/100000*'Client Inputs'!$B$24+'Client Inputs'!$B$9*E$14)*5-'ROI Summary'!$G$4)/'ROI Summary'!$G$4 -> 11.123966 | F17: =(('Client Inputs'!$B$6*$A17*'Client Inputs'!$B$13*'Client Inputs'!$B$28*'Client Inputs'!$B$29*'Client Inputs'!$B$30/100000+'Client Inputs'!$B$34+'Client Inputs'!$B$15*'Client Inputs'!$B$14/100000*'Client Inputs'!$B$24+'Client Inputs'!$B$9*F$14)*5-'ROI Summary'!$G$4)/'ROI Summary'!$G$4 -> 12.190621
A18: 0.2 | B18: =(('Client Inputs'!$B$6*$A18*'Client Inputs'!$B$13*'Client Inputs'!$B$28*'Client Inputs'!$B$29*'Client Inputs'!$B$30/100000+'Client Inputs'!$B$34+'Client Inputs'!$B$15*'Client Inputs'!$B$14/100000*'Client Inputs'!$B$24+'Client Inputs'!$B$9*B$14)*5-'ROI Summary'!$G$4)/'ROI Summary'!$G$4 -> 9.0657662 | C18: =(('Client Inputs'!$B$6*$A18*'Client Inputs'!$B$13*'Client Inputs'!$B$28*'Client Inputs'!$B$29*'Client Inputs'!$B$30/100000+'Client Inputs'!$B$34+'Client Inputs'!$B$15*'Client Inputs'!$B$14/100000*'Client Inputs'!$B$24+'Client Inputs'!$B$9*C$14)*5-'ROI Summary'!$G$4)/'ROI Summary'!$G$4 -> 9.7768695 | D18: =(('Client Inputs'!$B$6*$A18*'Client Inputs'!$B$13*'Client Inputs'!$B$28*'Client Inputs'!$B$29*'Client Inputs'!$B$30/100000+'Client Inputs'!$B$34+'Client Inputs'!$B$15*'Client Inputs'!$B$14/100000*'Client Inputs'!$B$24+'Client Inputs'!$B$9*D$14)*5-'ROI Summary'!$G$4)/'ROI Summary'!$G$4 -> 10.487973 | E18: =(('Client Inputs'!$B$6*$A18*'Client Inputs'!$B$13*'Client Inputs'!$B$28*'Client Inputs'!$B$29*'Client Inputs'!$B$30/100000+'Client Inputs'!$B$34+'Client Inputs'!$B$15*'Client Inputs'!$B$14/100000*'Client Inputs'!$B$24+'Client Inputs'!$B$9*E$14)*5-'ROI Summary'!$G$4)/'ROI Summary'!$G$4 -> 11.554628 | F18: =(('Client Inputs'!$B$6*$A18*'Client Inputs'!$B$13*'Client Inputs'!$B$28*'Client Inputs'!$B$29*'Client Inputs'!$B$30/100000+'Client Inputs'!$B$34+'Client Inputs'!$B$15*'Client Inputs'!$B$14/100000*'Client Inputs'!$B$24+'Client Inputs'!$B$9*F$14)*5-'ROI Summary'!$G$4)/'ROI Summary'!$G$4 -> 12.621283
A19: 0.25 | B19: =(('Client Inputs'!$B$6*$A19*'Client Inputs'!$B$13*'Client Inputs'!$B$28*'Client Inputs'!$B$29*'Client Inputs'!$B$30/100000+'Client Inputs'!$B$34+'Client Inputs'!$B$15*'Client Inputs'!$B$14/100000*'Client Inputs'!$B$24+'Client Inputs'!$B$9*B$14)*5-'ROI Summary'!$G$4)/'ROI Summary'!$G$4 -> 10.142421 | C19: =(('Client Inputs'!$B$6*$A19*'Client Inputs'!$B$13*'Client Inputs'!$B$28*'Client Inputs'!$B$29*'Client Inputs'!$B$30/100000+'Client Inputs'!$B$34+'Client Inputs'!$B$15*'Client Inputs'!$B$14/100000*'Client Inputs'!$B$24+'Client Inputs'!$B$9*C$14)*5-'ROI Summary'!$G$4)/'ROI Summary'!$G$4 -> 10.853524 | D19: =(('Client Inputs'!$B$6*$A19*'Client Inputs'!$B$13*'Client Inputs'!$B$28*'Client Inputs'!$B$29*'Client Inputs'!$B$30/100000+'Client Inputs'!$B$34+'Client Inputs'!$B$15*'Client Inputs'!$B$14/100000*'Client Inputs'!$B$24+'Client Inputs'!$B$9*D$14)*5-'ROI Summary'!$G$4)/'ROI Summary'!$G$4 -> 11.564628 | E19: =(('Client Inputs'!$B$6*$A19*'Client Inputs'!$B$13*'Client Inputs'!$B$28*'Client Inputs'!$B$29*'Client Inputs'!$B$30/100000+'Client Inputs'!$B$34+'Client Inputs'!$B$15*'Client Inputs'!$B$14/100000*'Client Inputs'!$B$24+'Client Inputs'!$B$9*E$14)*5-'ROI Summary'!$G$4)/'ROI Summary'!$G$4 -> 12.631283 | F19: =(('Client Inputs'!$B$6*$A19*'Client Inputs'!$B$13*'Client Inputs'!$B$28*'Client Inputs'!$B$29*'Client Inputs'!$B$30/100000+'Client Inputs'!$B$34+'Client Inputs'!$B$15*'Client Inputs'!$B$14/100000*'Client Inputs'!$B$24+'Client Inputs'!$B$9*F$14)*5-'ROI Summary'!$G$4)/'ROI Summary'!$G$4 -> 13.697938
A20: 0.3 | B20: =(('Client Inputs'!$B$6*$A20*'Client Inputs'!$B$13*'Client Inputs'!$B$28*'Client Inputs'!$B$29*'Client Inputs'!$B$30/100000+'Client Inputs'!$B$34+'Client Inputs'!$B$15*'Client Inputs'!$B$14/100000*'Client Inputs'!$B$24+'Client Inputs'!$B$9*B$14)*5-'ROI Summary'!$G$4)/'ROI Summary'!$G$4 -> 11.219076 | C20: =(('Client Inputs'!$B$6*$A20*'Client Inputs'!$B$13*'Client Inputs'!$B$28*'Client Inputs'!$B$29*'Client Inputs'!$B$30/100000+'Client Inputs'!$B$34+'Client Inputs'!$B$15*'Client Inputs'!$B$14/100000*'Client Inputs'!$B$24+'Client Inputs'!$B$9*C$14)*5-'ROI Summary'!$G$4)/'ROI Summary'!$G$4 -> 11.930179 | D20: =(('Client Inputs'!$B$6*$A20*'Client Inputs'!$B$13*'Client Inputs'!$B$28*'Client Inputs'!$B$29*'Client Inputs'!$B$30/100000+'Client Inputs'!$B$34+'Client Inputs'!$B$15*'Client Inputs'!$B$14/100000*'Client Inputs'!$B$24+'Client Inputs'!$B$9*D$14)*5-'ROI Summary'!$G$4)/'ROI Summary'!$G$4 -> 12.641283 | E20: =(('Client Inputs'!$B$6*$A20*'Client Inputs'!$B$13*'Client Inputs'!$B$28*'Client Inputs'!$B$29*'Client Inputs'!$B$30/100000+'Client Inputs'!$B$34+'Client Inputs'!$B$15*'Client Inputs'!$B$14/100000*'Client Inputs'!$B$24+'Client Inputs'!$B$9*E$14)*5-'ROI Summary'!$G$4)/'ROI Summary'!$G$4 -> 13.707938 | F20: =(('Client Inputs'!$B$6*$A20*'Client Inputs'!$B$13*'Client Inputs'!$B$28*'Client Inputs'!$B$29*'Client Inputs'!$B$30/100000+'Client Inputs'!$B$34+'Client Inputs'!$B$15*'Client Inputs'!$B$14/100000*'Client Inputs'!$B$24+'Client Inputs'!$B$9*F$14)*5-'ROI Summary'!$G$4)/'ROI Summary'!$G$4 -> 14.774592
A22: This grid is a simplified STATIC approximation (flat annual benefit × 5, no revenue growth or fee escalation) used purely to show directional sensitivity of 5-Year ROI% to EU export exposure and energy-savings assumptions. The highlighted cell approximates the current base-case inputs. See 'ROI Summary' for the full dynamic year-by-year model.

Sheet Assumptions & Sources
A1: ASSUMPTIONS & SOURCES
A3: Assumption | B3: Default Value | C3: Source / Rationale
A4: EU CBAM certificate price | B4: €85 / tCO2e | C4: Illustrative EU ETS/CBAM allowance price; verify against the live EU ETS price at proposal time before quoting to a client.
A5: EUR–INR exchange rate | B5: 95 | C5: Illustrative; update to the prevailing spot/forward rate at proposal time.
A6: CBAM default-value cost premium | B6: 30% | C6: Source: GF360 market research (Jul 2026) on EU default-value cost inflation applied in the absence of verified primary emissions data — relevant to any CBAM-exposed exporter, not sector-specific.
A7: Avoided annual consultant / Big-4 assessment fee | B7: Rs 35 Lakh (~US$40–50k) | C7: Source: GF360 market research — Big-4 tradition of one-off footprint assessments historically quoted at US$40,000–100,000+ globally across sectors; Indian boutique providers price below this for MSME-scale engagements.
A8: Energy efficiency savings ramp (Yr1 / Yr2 / Yr3+) | B8: 3% / 8% / 12% | C8: Illustrative decarbonisation-roadmap benchmark for Indian manufacturing MSMEs; typical realised savings range 8–15% over 2–3 years of a structured efficiency programme — validate per facility energy audit.
A9: Embedded emissions intensity | B9: 45 tCO2e / Rs Cr revenue | C9: Illustrative placeholder for a moderately energy-intensive manufacturing profile — varies widely by sector (e.g., higher for steel/cement/metals, lower for electronics/textiles/pharma). Replace with the client's actual Scope 1 & 2 emissions intensity once measured via the GF360 baseline assessment.
A10: GF360 tiered pricing (Starter / Growth / Enterprise) | B10: See 'Pricing Tiers' | C10: Source: GF360 Value-Based Tiered SaaS pricing strategy, aligned to the Indian/APAC bundled software + advisory market pattern documented in GF360 market research, applicable across manufacturing sectors.
A11: Automation efficiency gain on manual reporting | B11: 70% | C11: Illustrative — reflects typical reduction in person-days once data collection and reporting are automated on a structured MRV platform; validate against client's current process maturity.
A12: Probability-weighted revenue-at-risk without compliance | B12: 15% | C12: Illustrative risk-adjustment factor representing the expected share of EU/OEM-linked revenue exposed if the client cannot substantiate emissions data on request; shown separately from hard cost savings.
A13: GF360 risk-mitigation effectiveness | B13: 80% | C13: Illustrative — assumed share of the above revenue-at-risk that is protected once verified MRV data and reporting are in place.
A14: Discount rate / WACC | B14: 10% | C14: Illustrative WACC for an Indian mid-market manufacturer; the client should substitute their actual cost of capital.
... A20: Transport & logistics emission factors | B20: Indicative per tonne-km | C20: India GHG Program road-freight factors; Indian Railways (~10 gCO2/NTKM); GLEC-type averages for sea and air freight.
A22: Disclaimer: This is a modelling template for pre-sales / pitch purposes only. All client-specific figures (energy spend, turnover, export mix, actual embedded emissions) should be validated during discovery and scoping before this is used to support a binding commercial proposal.
